test/regFileALU.sv
//Creating ALU module
module regFileALU# (
    parameter Address_Width = 5,
              //ALU_Instruction_Width = 1;
              Data_Width = 32
) (
    //Interface signals
    input logic [Data_Width-1:0] op1, //input op1 into ALU which is output content from a register
    input logic [Data_Width-1:0] op2, //input op2 into ALU which is either 32-bit Imm or 32-bit content from register
    //input logic [ALU_Instruction_Width-1:0] ALU_ctrl,
    input logic [2:0] ALU_ctrl,
    output logic [Data_Width-1:0] ALUout, //output of ALU is same size as ALU inputs
    output logic eq //Eq is probably carry out flag
);

//ALU is not clocked component, it's combinational so:

always_comb begin //ALU implements different arithmetic/logic based on opcode input
    case (ALU_ctrl)
        3'b000: //Add Immediate:
            ALUout = op1 + op2; /* eq is irrelevant here as instruction for adding the two inputs would not need to consider/evaluate eq,
            so eq can be any value here */
            /* Similarly for bne, ALUout is irrelevant as only eq will be evaluated to check whether to jump to label or not */
        3'b111: //bne instruction:
            if(op1!=op2) eq = 0; //Eq is evaluated and if 0 and bne instruction then label is assigned
            else eq = 1;
        default: $display("Instruction not detected.");
    endcase
end
endmodule

test/regfileMux.sv
//Creating ALU Mux
//Now create top level design which connects regfile, mux, alu with wires

module regFileMux# (
    parameter Data_Width = 32

) (
    //Interface signals
    input logic [Data_Width-1:0] regOp2, //Output if mux select is 0
    input logic [Data_Width-1:0] ImmOp, //Output if mux select is 1
    input logic ALUSrc, //mux select
    output logic [Data_Width-1:0] ALUOp2 //2nd output of ALU
);

assign ALUOp2 = (ALUSrc) ? regOp2:ImmOp;

endmodule

test/regFile.sv
//Register file is just special type of RAM component so copy RAM template code:

module regFile # (
    parameter 
            // NumberOfReg = 32,
            Address_Width = 5, //32 registers so address size is 5 bits
            Data_Width = 32 //32-bit data
)(
    //Interface signals:
    //Assign input and output variables and their size:
    input logic clk,
    input logic [Address_Width-1:0] rs1, //32 registers so 5 bit address, rs1 is 1st source reg, arithmetic input
    input logic [Address_Width-1:0] rs2, //rs2 is 2nd source reg, arithmetic input
    input logic [Address_Width-1:0] rd, //rd is destination reg to store arithmetic output
    input logic en, //Enable to determine whether we can write to register file or not
    input logic [Data_Width-1:0] din, //Data in which takes in ALU output to write to register rd. Registers hold 32 bit word so din is 32 bits
    output logic [Data_Width-1:0] rd1, //32 bit word that is stored in register that is outputted to ALU for operation
    output logic [Data_Width-1:0] rd2, //32 bit word that is stored in register that is outputted to ALU for operation
    output logic [Data_Width-1:0] a0//Outputs data stored in a0 register

);

//Creating array of 32 32-bit registers:
logic [Data_Width-1:0] regFile_array [2**Address_Width-1:0]; //So 32-bit regfile with registers labelled 0 to 31

//Registers in regfile are not initialized to anything so neither contents = 0 or contents are empty, so add rst which sets all content values to 0
initial begin 
        $display("Initializing regFile with null values (0).");
        $readmemh("regFile.mem", regFile_array); 
end;

//Register file is sequential (clocked) so only at rising edge we output the value stored at register given by regFile_array[rs1]
always_ff @ (posedge clk) begin
    //At rising edge do:
    rd1 <= regFile_array [rs1];
    rd2 <= regFile_array [rs2];
    if (en)     regFile_array[rd] <= din; //so at rising edge also the din is stored at register given by address rd
    
end

assign a0 = regFile_array[5'd10];

endmodule
//So this is all code for the regfile

test/topLevelALU.sv
module topLevelALU# (
    parameter NumberOfReg = 32,
              Address_Width = 5, //32 registers so address size is 5 bits
              Data_Width = 32
              //ALU_Instruction_Width = 10;
) (
//Interface Signals
    input logic clk,
    input logic [Address_Width-1:0] rs1, //32 registers so 5 bit address, rs1 is 1st source reg, arithmetic input
    input logic [Address_Width-1:0] rs2, //rs2 is 2nd source reg, arithmetic input
    input logic [Address_Width-1:0] rd, //rd is destination reg to store arithmetic output
    input logic en, //Enable to determine whether we can write to register file or not
    input logic [Data_Width-1:0] din, //Data in which takes in ALU output to write to register rd. Registers hold 32 bit word so din is 32 bits
    input logic ALUSrc,
    input logic [Data_Width-1:0] ImmOp,
    //input logic [ALU_Instruction_Width-1:0] ALU_ctrl;
    input logic [2:0] ALU_ctrl,
//Outputs
    output logic [Data_Width-1:0] ALUout, //output of ALU is same size as ALU inputs
    output logic eq,
    output logic [Data_Width-1:0] a0
);

//Variable which acts in the middle:
logic [Data_Width-1:0] rd1;
logic [Data_Width-1:0] rd2;
logic [Data_Width-1:0] ALUOp2;

//Initializing objects of the different modules and linking them
regFile regFile1 (clk, rs1, rs2, rd, en, din, rd1, rd2, a0);
regFileMux mux1 (rd2, ImmOp, ALUsrc, ALUOp2);
regFileALU alu1 (rd1, ALUOp2, ALU_ctrl, ALUout, eq);

endmodule

test/control.sv
module control(
    input logic         EQ,
    input logic [6:0]   instr_opcode,

    output logic RegWrite,
    output logic[2:0] ALUctrl,
    output logic ALUsrc,
    output logic ImmSrc,
    output logic PCsrc
);


always_comb begin

    case(instr_opcode)
        7'b0010011: begin ALUctrl = 3'b000;
                          RegWrite = 1;
                          ALUsrc = 1;
                          ImmSrc = 1;
                          PCsrc = 0;
        end 

    
        7'b1100011: begin ALUctrl = 3'b111;
                          RegWrite = 0;
                          ALUsrc = 0;
                          ImmSrc = 0;
                          PCsrc = ~EQ;
        end

        default: begin
            ALUsrc = 0;
            ImmSrc = 0;
            PCsrc = 0;
        end

    endcase
    
end
    
endmodule

test/ext.sv
module ext(
    // input clk,
    // input logic [31:0] inst,
    input logic [11:0] imm_imm, // imm value when the instruction format is immediate
    input logic [11:0] imm_branch, // imm value when the instruction format is branch
    input logic ImmSrc,
    output logic [31:0] ImmOp
);

    logic [11:0] imm;

    always_comb begin
        if (ImmSrc) 
        imm = imm_imm;

        else 
        imm = imm_branch;



        ImmOp = {{20{imm[11]}}, imm[11:0]};
    end

endmodule

test/rom.sv
module rom #(
    parameter ADDRESS_WIDTH = 8,// should be 32 bits but having some trouble accommodating memory.
    DATA_WIDTH = 32 // data width of each instruction has to be 32 to accommodate all possible instructions
)(
    input logic [ADDRESS_WIDTH-1:0] PC,
    output logic [DATA_WIDTH-1:0]   instr
);

logic [DATA_WIDTH-1:0] rom_array [2**ADDRESS_WIDTH-1:0];

initial begin
    $display("Loading rom.");
    $readmemh("instructions.mem", rom_array);
    $display("Rom successfully loaded.");
end;

// asynchronous assignment, should be blocking
assign instr = rom_array[PC];

endmodule

test/pcreg.sv
module pcreg #(
    parameter ADDRESS_WIDTH = 8
)(
    // inputs and corresponding outputs from left to right
    input logic [ADDRESS_WIDTH-1:0] ImmOp,
    input logic                     PCsrc,
    input logic                     clk,
    input logic                     rst,
    output logic [ADDRESS_WIDTH-1:0] PC
);

    logic [ADDRESS_WIDTH-1:0] branch_PC;
    logic [ADDRESS_WIDTH-1:0] inc_PC;

initial begin
    PC = {ADDRESS_WIDTH{1'b0}};
end

// intermediate output from the mux block, should be decided based on the value of PCsrc
logic [ADDRESS_WIDTH-1:0] next_PC;

// handles assigning individual control values to the mux block
assign branch_PC = PC + ImmOp;
assign inc_PC = PC + 8'h4;


// handles the mux block
assign next_PC = PCsrc ? branch_PC : inc_PC;

// handles the PC register, note that this part is clocked
always_ff @(posedge clk)
    // synchronous reset
    if(rst) PC <= {ADDRESS_WIDTH{1'b0}};
    else    PC <= next_PC;

endmodule

test/PC.sv
module PC #(
        parameter ADDRESS_WIDTH = 8,
        IMMOP_WIDTH = 32, // just a workaround at the moment, will work fine for now but need to figure out why memory alloation isn't taking place accurately.
    DATA_WIDTH = 32
)(
  input logic [IMMOP_WIDTH-1:0] ImmOp,
  input logic                     PCsrc,
  input logic                     clk,
  input logic                     rst,
  output logic [DATA_WIDTH-1:0]   instr
);

  logic [ADDRESS_WIDTH-1:0] PC;
  logic [ADDRESS_WIDTH-1:0] ImmOp_intermed;

  assign ImmOp_intermed = ImmOp[ADDRESS_WIDTH-1:0];

pcreg myPCreg (
  .ImmOp(ImmOp_intermed),
  .PC(PC),
  .PCsrc(PCsrc),
  .clk (clk),
  .rst (rst)
);

rom myRom (
  .PC(PC),
  .instr(instr)
);

endmodule

test/top.sv
module top#(
    parameter ADDRESS_WIDTH = 32,
    DATA_WIDTH = 32
)(
    input logic             clk,
    input logic             rst,
    //don't need write function yet, so used this as input
    output [31:0]   trash,
    output logic [ADDRESS_WIDTH-1:0] a0,


    output logic wr_en,
    output logic Eq,
    output logic alusrc,
    output logic[2:0] aluCtrl,
    output logic[31:0] extout,
    output logic [DATA_WIDTH - 1:0] aluout


);

    logic             write_en;
    logic [DATA_WIDTH-1:0] PC_instr;
    logic PC_src;
    logic [4:0] rs1;
    logic [4:0] rs2;
    logic [4:0] rd;
    logic [DATA_WIDTH-1:0] write_data;
    logic ALU_src;
    logic [2:0] ALU_ctrl;
    logic EQ;
    logic [DATA_WIDTH-1:0] ImmOp;
    logic [DATA_WIDTH-1:0] ALUout;

    logic [11:0] imm_imm;
    logic [11:0] imm_branch;

    assign rs1 = PC_instr[19:15];
    assign rs2 = PC_instr[24:20];
    assign rd  = PC_instr[24:20];
    

    assign trash = PC_instr;
PC myPC(
    .ImmOp  (ImmOp),
    .PCsrc  (PC_src),
    .clk    (clk),
    .rst    (rst),
    .instr   (PC_instr)
);

assign imm_imm = PC_instr[31:20];
assign imm_branch = {PC_instr[31],PC_instr[7],PC_instr[30:25],PC_instr[11:8]};

ext sign_extend(
    //.clk    (clk),
    // .inst   (PC_instr),
    .imm_imm (imm_imm),
    .imm_branch (imm_branch),
    .ImmSrc (ImmSrc),
    .ImmOp  (ImmOp)
);

control control_unit(
    .EQ     (EQ),
    .instr_opcode  (PC_instr[6:0]),
    .RegWrite   (write_en),
    .ALUctrl    (ALU_ctrl),
    .ALUsrc     (ALU_src),
    .ImmSrc     (ImmSrc),
    .PCsrc      (PC_src)
);
topLevelALU ALU(
    .clk    (clk),
    .rs1    (rs1),
    .rs2    (rs2),
    .rd     (rd),
    .en     (write_en),
    .din    (write_data),
    .ALUSrc (ALU_src),
    .ImmOp  (ImmOp),
    .ALU_ctrl (ALU_ctrl),
    .ALUout (ALUout),
    .eq     (EQ),
    .a0     (a0)
);

assign aluout = ALUout;
assign aluCtrl = ALU_ctrl;
assign wr_en = write_en;
assign Eq = EQ;
assign extout = ImmOp;
assign alusrc = ALU_src;


endmodule

test/top.vcd
$version Generated by VerilatedVcd $end
$date Tue Nov 22 21:19:43 2022 $end
$timescale 1ps $end

 $scope module TOP $end
  $var wire  1 ^ Eq $end
  $var wire 32 \ a0 [31:0] $end
  $var wire  3 ` aluCtrl [2:0] $end
  $var wire 32 b aluout [31:0] $end
  $var wire  1 _ alusrc $end
  $var wire  1 Y clk $end
  $var wire 32 a extout [31:0] $end
  $var wire  1 Z rst $end
  $var wire 32 [ trash [31:0] $end
  $var wire  1 ] wr_en $end
  $scope module top $end
   $var wire 32 c ADDRESS_WIDTH [31:0] $end
   $var wire  3 ) ALU_ctrl [2:0] $end
   $var wire  1 ( ALU_src $end
   $var wire 32 , ALUout [31:0] $end
   $var wire 32 c DATA_WIDTH [31:0] $end
   $var wire  1 * EQ $end
   $var wire  1 ^ Eq $end
   $var wire 32 + ImmOp [31:0] $end
   $var wire  1 ( ImmSrc $end
   $var wire 32 $ PC_instr [31:0] $end
   $var wire  1 % PC_src $end
   $var wire 32 \ a0 [31:0] $end
   $var wire  3 ` aluCtrl [2:0] $end
   $var wire 32 b aluout [31:0] $end
   $var wire  1 _ alusrc $end
   $var wire  1 Y clk $end
   $var wire 32 a extout [31:0] $end
   $var wire 12 . imm_branch [11:0] $end
   $var wire 12 - imm_imm [11:0] $end
   $var wire  5 ' rd [4:0] $end
   $var wire  5 & rs1 [4:0] $end
   $var wire  5 ' rs2 [4:0] $end
   $var wire  1 Z rst $end
   $var wire 32 [ trash [31:0] $end
   $var wire  1 ] wr_en $end
   $var wire 32 d write_data [31:0] $end
   $var wire  1 # write_en $end
   $scope module ALU $end
    $var wire 32 1 ALUOp2 [31:0] $end
    $var wire  1 ( ALUSrc $end
    $var wire  3 ) ALU_ctrl [2:0] $end
    $var wire 32 , ALUout [31:0] $end
    $var wire 32 e Address_Width [31:0] $end
    $var wire 32 c Data_Width [31:0] $end
    $var wire 32 + ImmOp [31:0] $end
    $var wire 32 \ a0 [31:0] $end
    $var wire  1 Y clk $end
    $var wire 32 d din [31:0] $end
    $var wire  1 # en $end
    $var wire  1 * eq $end
    $var wire  5 ' rd [4:0] $end
    $var wire 32 / rd1 [31:0] $end
    $var wire 32 0 rd2 [31:0] $end
    $var wire  5 & rs1 [4:0] $end
    $var wire  5 ' rs2 [4:0] $end
    $scope module alu1 $end
     $var wire  3 ) ALU_ctrl [2:0] $end
     $var wire 32 , ALUout [31:0] $end
     $var wire 32 c Data_Width [31:0] $end
     $var wire  1 * eq $end
     $var wire 32 / op1 [31:0] $end
     $var wire 32 1 op2 [31:0] $end
    $upscope $end
    $scope module mux1 $end
     $var wire 32 1 ALUOp2 [31:0] $end
     $var wire  1 ( ALUSrc $end
     $var wire 32 c Data_Width [31:0] $end
     $var wire 32 + ImmOp [31:0] $end
     $var wire 32 0 regOp2 [31:0] $end
    $upscope $end
    $scope module regFile1 $end
     $var wire 32 e Address_Width [31:0] $end
     $var wire 32 c Data_Width [31:0] $end
     $var wire 32 \ a0 [31:0] $end
     $var wire  1 Y clk $end
     $var wire 32 d din [31:0] $end
     $var wire  1 # en $end
     $var wire  5 ' rd [4:0] $end
     $var wire 32 / rd1 [31:0] $end
     $var wire 32 0 rd2 [31:0] $end
     $var wire 32 2 regFile_array[0] [31:0] $end
     $var wire 32 < regFile_array[10] [31:0] $end
     $var wire 32 = regFile_array[11] [31:0] $end
     $var wire 32 > regFile_array[12] [31:0] $end
     $var wire 32 ? regFile_array[13] [31:0] $end
     $var wire 32 @ regFile_array[14] [31:0] $end
     $var wire 32 A regFile_array[15] [31:0] $end
     $var wire 32 B regFile_array[16] [31:0] $end
     $var wire 32 C regFile_array[17] [31:0] $end
     $var wire 32 D regFile_array[18] [31:0] $end
     $var wire 32 E regFile_array[19] [31:0] $end
     $var wire 32 3 regFile_array[1] [31:0] $end
     $var wire 32 F regFile_array[20] [31:0] $end
     $var wire 32 G regFile_array[21] [31:0] $end
     $var wire 32 H regFile_array[22] [31:0] $end
     $var wire 32 I regFile_array[23] [31:0] $end
     $var wire 32 J regFile_array[24] [31:0] $end
     $var wire 32 K regFile_array[25] [31:0] $end
     $var wire 32 L regFile_array[26] [31:0] $end
     $var wire 32 M regFile_array[27] [31:0] $end
     $var wire 32 N regFile_array[28] [31:0] $end
     $var wire 32 O regFile_array[29] [31:0] $end
     $var wire 32 4 regFile_array[2] [31:0] $end
     $var wire 32 P regFile_array[30] [31:0] $end
     $var wire 32 Q regFile_array[31] [31:0] $end
     $var wire 32 5 regFile_array[3] [31:0] $end
     $var wire 32 6 regFile_array[4] [31:0] $end
     $var wire 32 7 regFile_array[5] [31:0] $end
     $var wire 32 8 regFile_array[6] [31:0] $end
     $var wire 32 9 regFile_array[7] [31:0] $end
     $var wire 32 : regFile_array[8] [31:0] $end
     $var wire 32 ; regFile_array[9] [31:0] $end
     $var wire  5 & rs1 [4:0] $end
     $var wire  5 ' rs2 [4:0] $end
    $upscope $end
   $upscope $end
   $scope module control_unit $end
    $var wire  3 ) ALUctrl [2:0] $end
    $var wire  1 ( ALUsrc $end
    $var wire  1 * EQ $end
    $var wire  1 ( ImmSrc $end
    $var wire  1 % PCsrc $end
    $var wire  1 # RegWrite $end
    $var wire  7 R instr_opcode [6:0] $end
   $upscope $end
   $scope module myPC $end
    $var wire 32 f ADDRESS_WIDTH [31:0] $end
    $var wire 32 c DATA_WIDTH [31:0] $end
    $var wire 32 c IMMOP_WIDTH [31:0] $end
    $var wire 32 + ImmOp [31:0] $end
    $var wire  8 T ImmOp_intermed [7:0] $end
    $var wire  8 S PC [7:0] $end
    $var wire  1 % PCsrc $end
    $var wire  1 Y clk $end
    $var wire 32 $ instr [31:0] $end
    $var wire  1 Z rst $end
    $scope module myPCreg $end
     $var wire 32 f ADDRESS_WIDTH [31:0] $end
     $var wire  8 T ImmOp [7:0] $end
     $var wire  8 S PC [7:0] $end
     $var wire  1 % PCsrc $end
     $var wire  8 U branch_PC [7:0] $end
     $var wire  1 Y clk $end
     $var wire  8 V inc_PC [7:0] $end
     $var wire  8 W next_PC [7:0] $end
     $var wire  1 Z rst $end
    $upscope $end
    $scope module myRom $end
     $var wire 32 f ADDRESS_WIDTH [31:0] $end
     $var wire 32 c DATA_WIDTH [31:0] $end
     $var wire  8 S PC [7:0] $end
     $var wire 32 $ instr [31:0] $end
    $upscope $end
   $upscope $end
   $scope module sign_extend $end
    $var wire 32 + ImmOp [31:0] $end
    $var wire  1 ( ImmSrc $end
    $var wire 12 X imm [11:0] $end
    $var wire 12 . imm_branch [11:0] $end
    $var wire 12 - imm_imm [11:0] $end
   $upscope $end
  $upscope $end
 $upscope $end
$enddefinitions $end


#0
0#
b00000000000000000000000000000000 $
0%
b00000 &
b00000 '
0(
b000 )
0*
b00000000000000000000000000000000 +
b00000000000000000000000000000000 ,
b000000000000 -
b000000000000 .
b00000000000000000000000000000000 /
b00000000000000000000000000000000 0
b00000000000000000000000000000000 1
b00000000000000000000000000000000 2
b00000000000000000000000000000000 3
b00000000000000000000000000000000 4
b00000000000000000000000000000000 5
b00000000000000000000000000000000 6
b00000000000000000000000000000000 7
b00000000000000000000000000000000 8
b00000000000000000000000000000000 9
b00000000000000000000000000000000 :
b00000000000000000000000000000000 ;
b00000000000000000000000000000000 <
b00000000000000000000000000000000 =
b00000000000000000000000000000000 >
b00000000000000000000000000000000 ?
b00000000000000000000000000000000 @
b00000000000000000000000000000000 A
b00000000000000000000000000000000 B
b00000000000000000000000000000000 C
b00000000000000000000000000000000 D
b00000000000000000000000000000000 E
b00000000000000000000000000000000 F
b00000000000000000000000000000000 G
b00000000000000000000000000000000 H
b00000000000000000000000000000000 I
b00000000000000000000000000000000 J
b00000000000000000000000000000000 K
b00000000000000000000000000000000 L
b00000000000000000000000000000000 M
b00000000000000000000000000000000 N
b00000000000000000000000000000000 O
b00000000000000000000000000000000 P
b00000000000000000000000000000000 Q
b0000000 R
b00000000 S
b00000000 T
b00000000 U
b00000100 V
b00000100 W
b000000000000 X
0Y
0Z
b00000000000000000000000000000000 [
b00000000000000000000000000000000 \
0]
0^
0_
b000 `
b00000000000000000000000000000000 a
b00000000000000000000000000000000 b
b00000000000000000000000000100000 c
b00000000000000000000000000000000 d
b00000000000000000000000000000101 e
b00000000000000000000000000001000 f
#1
1#
b00001111111100000000001100010011 $
b11111 '
1(
b00000000000000000000000011111111 +
b00000000000000000000000011111111 ,
b000011111111 -
b000001110011 .
b00000000000000000000000011111111 1
b0010011 R
b11111111 T
b11111111 U
b000011111111 X
1Y
b00001111111100000000001100010011 [
1]
1_
b00000000000000000000000011111111 a
b00000000000000000000000011111111 b
#2
0Y
#3
b00000000000000000000010100010011 $
b00000 '
b00000000000000000000000000000000 +
b00000000000000000000000000000000 ,
b000000000000 -
b000000000101 .
b00000000000000000000000000000000 1
b00000100 S
b00000000 T
b00000100 U
b00001000 V
b00001000 W
b000000000000 X
1Y
b00000000000000000000010100010011 [
b00000000000000000000000000000000 a
b00000000000000000000000000000000 b
#4
0Y
#5
b00000000000000000000010110010011 $
b010000000101 .
b00001000 S
b00001000 U
b00001100 V
b00001100 W
1Y
b00000000000000000000010110010011 [
#6
0Y
#7
b00000000000001011000010100010011 $
b01011 &
b000000000101 .
b00001100 S
b00001100 U
b00010000 V
b00010000 W
1Y
b00000000000001011000010100010011 [
#8
0Y
#9
b00000000000101011000010110010011 $
b00001 '
b00000000000000000000000000000001 +
b00000000000000000000000000000001 ,
b000000000001 -
b010000000101 .
b00000000000000000000000000000001 1
b00010000 S
b00000001 T
b00010001 U
b00010100 V
b00010100 W
b000000000001 X
1Y
b00000000000101011000010110010011 [
b00000000000000000000000000000001 a
b00000000000000000000000000000001 b
#10
0Y
#11
0#
b11111110011001011001110011100011 $
b00110 '
0(
b111 )
1*
b11111111111111111111111111111100 +
b111111100110 -
b111111111100 .
b00000000000000000000000000000000 1
b1100011 R
b00010100 S
b11111100 T
b00010000 U
b00011000 V
b00011000 W
b111111111100 X
1Y
b11111110011001011001110011100011 [
0]
1^
0_
b111 `
b11111111111111111111111111111100 a
#12
0Y
#13
b11111110000000110000100011100011 $
b00110 &
b00000 '
b11111111111111111111111111111000 +
b111111100000 -
b111111111000 .
b00011000 S
b11111000 T
b00011100 V
b00011100 W
b111111111000 X
1Y
b11111110000000110000100011100011 [
b11111111111111111111111111111000 a
#14
0Y
#15
b00000000000000000000000000000000 $
b00000 &
b00000000000000000000000000000000 +
b000000000000 -
b000000000000 .
b0000000 R
b00011100 S
b00000000 T
b00011100 U
b00100000 V
b00100000 W
b000000000000 X
1Y
b00000000000000000000000000000000 [
b00000000000000000000000000000000 a
#16
0Y
#17
b00100000 S
b00100000 U
b00100100 V
b00100100 W
1Y
#18
0Y
#19
b00100100 S
b00100100 U
b00101000 V
b00101000 W
1Y
#20
0Y
#21
b00101000 S
b00101000 U
b00101100 V
b00101100 W
1Y
#22
0Y
#23
b00101100 S
b00101100 U
b00110000 V
b00110000 W
1Y
#24
0Y
#25
b00110000 S
b00110000 U
b00110100 V
b00110100 W
1Y
#26
0Y
#27
b00110100 S
b00110100 U
b00111000 V
b00111000 W
1Y
#28
0Y
#29
b00111000 S
b00111000 U
b00111100 V
b00111100 W
1Y
#30
0Y
#31
b00111100 S
b00111100 U
b01000000 V
b01000000 W
1Y
#32
0Y
#33
b01000000 S
b01000000 U
b01000100 V
b01000100 W
1Y
#34
0Y
#35
b01000100 S
b01000100 U
b01001000 V
b01001000 W
1Y
#36
0Y
#37
b01001000 S
b01001000 U
b01001100 V
b01001100 W
1Y
#38
0Y
#39
b01001100 S
b01001100 U
b01010000 V
b01010000 W
1Y
#40
0Y
#41
b01010000 S
b01010000 U
b01010100 V
b01010100 W
1Y
#42
0Y
#43
b01010100 S
b01010100 U
b01011000 V
b01011000 W
1Y
#44
0Y
#45
b01011000 S
b01011000 U
b01011100 V
b01011100 W
1Y
#46
0Y
#47
b01011100 S
b01011100 U
b01100000 V
b01100000 W
1Y
#48
0Y
#49
b01100000 S
b01100000 U
b01100100 V
b01100100 W
1Y
#50
0Y
#51
b01100100 S
b01100100 U
b01101000 V
b01101000 W
1Y
#52
0Y
#53
b01101000 S
b01101000 U
b01101100 V
b01101100 W
1Y
#54
0Y
#55
b01101100 S
b01101100 U
b01110000 V
b01110000 W
1Y
#56
0Y
#57
b01110000 S
b01110000 U
b01110100 V
b01110100 W
1Y
#58
0Y
#59
b01110100 S
b01110100 U
b01111000 V
b01111000 W
1Y
#60
0Y
#61
b01111000 S
b01111000 U
b01111100 V
b01111100 W
1Y
#62
0Y
#63
b01111100 S
b01111100 U
b10000000 V
b10000000 W
1Y
#64
0Y
#65
b10000000 S
b10000000 U
b10000100 V
b10000100 W
1Y
#66
0Y
#67
b10000100 S
b10000100 U
b10001000 V
b10001000 W
1Y
#68
0Y
#69
b10001000 S
b10001000 U
b10001100 V
b10001100 W
1Y
#70
0Y
#71
b10001100 S
b10001100 U
b10010000 V
b10010000 W
1Y
#72
0Y
#73
b10010000 S
b10010000 U
b10010100 V
b10010100 W
1Y
#74
0Y
#75
b10010100 S
b10010100 U
b10011000 V
b10011000 W
1Y
#76
0Y
#77
b10011000 S
b10011000 U
b10011100 V
b10011100 W
1Y
#78
0Y
#79
b10011100 S
b10011100 U
b10100000 V
b10100000 W
1Y
#80
0Y
#81
b10100000 S
b10100000 U
b10100100 V
b10100100 W
1Y
#82
0Y
#83
b10100100 S
b10100100 U
b10101000 V
b10101000 W
1Y
#84
0Y
#85
b10101000 S
b10101000 U
b10101100 V
b10101100 W
1Y
#86
0Y
#87
b10101100 S
b10101100 U
b10110000 V
b10110000 W
1Y
#88
0Y
#89
b10110000 S
b10110000 U
b10110100 V
b10110100 W
1Y
#90
0Y
#91
b10110100 S
b10110100 U
b10111000 V
b10111000 W
1Y
#92
0Y
#93
b10111000 S
b10111000 U
b10111100 V
b10111100 W
1Y
#94
0Y
#95
b10111100 S
b10111100 U
b11000000 V
b11000000 W
1Y
#96
0Y
#97
b11000000 S
b11000000 U
b11000100 V
b11000100 W
1Y
#98
0Y
#99
b11000100 S
b11000100 U
b11001000 V
b11001000 W
1Y
#100
0Y
#101
b11001000 S
b11001000 U
b11001100 V
b11001100 W
1Y
#102
0Y
#103
b11001100 S
b11001100 U
b11010000 V
b11010000 W
1Y
#104
0Y
#105
b11010000 S
b11010000 U
b11010100 V
b11010100 W
1Y
#106
0Y
#107
b11010100 S
b11010100 U
b11011000 V
b11011000 W
1Y
#108
0Y
#109
b11011000 S
b11011000 U
b11011100 V
b11011100 W
1Y
#110
0Y
#111
b11011100 S
b11011100 U
b11100000 V
b11100000 W
1Y
#112
0Y
#113
b11100000 S
b11100000 U
b11100100 V
b11100100 W
1Y
#114
0Y
#115
b11100100 S
b11100100 U
b11101000 V
b11101000 W
1Y
#116
0Y
#117
b11101000 S
b11101000 U
b11101100 V
b11101100 W
1Y
#118
0Y
#119
b11101100 S
b11101100 U
b11110000 V
b11110000 W
1Y
#120
0Y
#121
b11110000 S
b11110000 U
b11110100 V
b11110100 W
1Y
#122
0Y
#123
b11110100 S
b11110100 U
b11111000 V
b11111000 W
1Y
#124
0Y
#125
b11111000 S
b11111000 U
b11111100 V
b11111100 W
1Y
#126
0Y
#127
b11111100 S
b11111100 U
b00000000 V
b00000000 W
1Y
#128
0Y
#129
1#
b00001111111100000000001100010011 $
b11111 '
1(
b000 )
b00000000000000000000000011111111 +
b00000000000000000000000011111111 ,
b000011111111 -
b000001110011 .
b00000000000000000000000011111111 1
b0010011 R
b00000000 S
b11111111 T
b11111111 U
b00000100 V
b00000100 W
b000011111111 X
1Y
b00001111111100000000001100010011 [
1]
1_
b000 `
b00000000000000000000000011111111 a
b00000000000000000000000011111111 b
#130
0Y
#131
b00000000000000000000010100010011 $
b00000 '
b00000000000000000000000000000000 +
b00000000000000000000000000000000 ,
b000000000000 -
b000000000101 .
b00000000000000000000000000000000 1
b00000100 S
b00000000 T
b00000100 U
b00001000 V
b00001000 W
b000000000000 X
1Y
b00000000000000000000010100010011 [
b00000000000000000000000000000000 a
b00000000000000000000000000000000 b
#132
0Y
#133
b00000000000000000000010110010011 $
b010000000101 .
b00001000 S
b00001000 U
b00001100 V
b00001100 W
1Y
b00000000000000000000010110010011 [
#134
0Y
#135
b00000000000001011000010100010011 $
b01011 &
b000000000101 .
b00001100 S
b00001100 U
b00010000 V
b00010000 W
1Y
b00000000000001011000010100010011 [
#136
0Y
#137
b00000000000101011000010110010011 $
b00001 '
b00000000000000000000000000000001 +
b00000000000000000000000000000001 ,
b000000000001 -
b010000000101 .
b00000000000000000000000000000001 1
b00010000 S
b00000001 T
b00010001 U
b00010100 V
b00010100 W
b000000000001 X
1Y
b00000000000101011000010110010011 [
b00000000000000000000000000000001 a
b00000000000000000000000000000001 b
#138
0Y
#139
0#
b11111110011001011001110011100011 $
b00110 '
0(
b111 )
b11111111111111111111111111111100 +
b111111100110 -
b111111111100 .
b00000000000000000000000000000000 1
b1100011 R
b00010100 S
b11111100 T
b00010000 U
b00011000 V
b00011000 W
b111111111100 X
1Y
b11111110011001011001110011100011 [
0]
0_
b111 `
b11111111111111111111111111111100 a
#140
0Y
#141
b11111110000000110000100011100011 $
b00110 &
b00000 '
b11111111111111111111111111111000 +
b111111100000 -
b111111111000 .
b00011000 S
b11111000 T
b00011100 V
b00011100 W
b111111111000 X
1Y
b11111110000000110000100011100011 [
b11111111111111111111111111111000 a
#142
0Y
#143
b00000000000000000000000000000000 $
b00000 &
b00000000000000000000000000000000 +
b000000000000 -
b000000000000 .
b0000000 R
b00011100 S
b00000000 T
b00011100 U
b00100000 V
b00100000 W
b000000000000 X
1Y
b00000000000000000000000000000000 [
b00000000000000000000000000000000 a
#144
0Y
#145
b00100000 S
b00100000 U
b00100100 V
b00100100 W
1Y
#146
0Y
#147
b00100100 S
b00100100 U
b00101000 V
b00101000 W
1Y
#148
0Y
#149
b00101000 S
b00101000 U
b00101100 V
b00101100 W
1Y
#150
0Y
#151
b00101100 S
b00101100 U
b00110000 V
b00110000 W
1Y
#152
0Y
#153
b00110000 S
b00110000 U
b00110100 V
b00110100 W
1Y
#154
0Y
#155
b00110100 S
b00110100 U
b00111000 V
b00111000 W
1Y
#156
0Y
#157
b00111000 S
b00111000 U
b00111100 V
b00111100 W
1Y
#158
0Y
#159
b00111100 S
b00111100 U
b01000000 V
b01000000 W
1Y
#160
0Y
#161
b01000000 S
b01000000 U
b01000100 V
b01000100 W
1Y
#162
0Y
#163
b01000100 S
b01000100 U
b01001000 V
b01001000 W
1Y
#164
0Y
#165
b01001000 S
b01001000 U
b01001100 V
b01001100 W
1Y
#166
0Y
#167
b01001100 S
b01001100 U
b01010000 V
b01010000 W
1Y
#168
0Y
#169
b01010000 S
b01010000 U
b01010100 V
b01010100 W
1Y
#170
0Y
#171
b01010100 S
b01010100 U
b01011000 V
b01011000 W
1Y
#172
0Y
#173
b01011000 S
b01011000 U
b01011100 V
b01011100 W
1Y
#174
0Y
#175
b01011100 S
b01011100 U
b01100000 V
b01100000 W
1Y
#176
0Y
#177
b01100000 S
b01100000 U
b01100100 V
b01100100 W
1Y
#178
0Y
#179
b01100100 S
b01100100 U
b01101000 V
b01101000 W
1Y
#180
0Y
#181
b01101000 S
b01101000 U
b01101100 V
b01101100 W
1Y
#182
0Y
#183
b01101100 S
b01101100 U
b01110000 V
b01110000 W
1Y
#184
0Y
#185
b01110000 S
b01110000 U
b01110100 V
b01110100 W
1Y
#186
0Y
#187
b01110100 S
b01110100 U
b01111000 V
b01111000 W
1Y
#188
0Y
#189
b01111000 S
b01111000 U
b01111100 V
b01111100 W
1Y
#190
0Y
