PC/rom.sv
module rom #(
    parameter ADDRESS_WIDTH = 32,// should be 32 bits but having some trouble accommodating memory.
    DATA_WIDTH = 8 // data width of each instruction has to be 32 to accommodate all possible instructions
)(
    input logic [ADDRESS_WIDTH-1:0] PC,
    output logic [31:0]   instr
);

logic [DATA_WIDTH-1:0] rom_array [27:0];

initial begin
    $display("Loading rom.");
    $readmemh("instructions.mem", rom_array);
    $display("Rom successfully loaded.");
end;

// asynchronous assignment, should be blocking
assign instr = {rom_array[PC], rom_array[PC+1], rom_array[PC+2], rom_array[PC+3]};

endmodule

PC/pcreg.sv
module pcreg #(
    parameter ADDRESS_WIDTH = 8
)(
    // inputs and corresponding outputs from left to right
    input logic [ADDRESS_WIDTH-1:0] ImmOp,
    input logic                     PCsrc,
    input logic                     clk,
    input logic                     rst,
    output logic [ADDRESS_WIDTH-1:0] PC
);

    logic [ADDRESS_WIDTH-1:0] branch_PC;
    logic [ADDRESS_WIDTH-1:0] inc_PC;

initial begin
    PC = {ADDRESS_WIDTH{1'b0}};
end

// intermediate output from the mux block, should be decided based on the value of PCsrc
logic [ADDRESS_WIDTH-1:0] next_PC;

// handles assigning individual control values to the mux block
assign branch_PC = PC + ImmOp;
assign inc_PC = PC + 8'h4;


// handles the mux block
assign next_PC = PCsrc ? branch_PC : inc_PC;

// handles the PC register, note that this part is clocked
always_ff @(posedge clk)
    // synchronous reset
    if(rst) PC <= {ADDRESS_WIDTH{1'b0}};
    else    PC <= next_PC;

endmodule

PC/PC_top.sv
module PC_top #(
        parameter ADDRESS_WIDTH = 32, // just a workaround at the moment, will work fine for now but need to figure out why memory allocation isn't taking place accurately.
    DATA_WIDTH = 32
)(
  input logic [ADDRESS_WIDTH-1:0] ImmOp,
  input logic                     PCsrc,
  input logic                     clk,
  input logic                     rst,
  output logic [DATA_WIDTH-1:0]   instr
);

  logic [ADDRESS_WIDTH-1:0] PC;

pcreg myPCreg(ImmOp, PCsrc, clk, rst, PC);

rom myRom(PC, instr);

endmodule

PC/PC_top.vcd
$version Generated by VerilatedVcd $end
$date Fri Dec  2 15:17:30 2022 $end
$timescale 1ps $end

 $scope module TOP $end
  $var wire 32 ? ImmOp [31:0] $end
  $var wire  1 @ PCsrc $end
  $var wire  1 A clk $end
  $var wire 32 C instr [31:0] $end
  $var wire  1 B rst $end
  $scope module PC_top $end
   $var wire 32 H ADDRESS_WIDTH [31:0] $end
   $var wire 32 H DATA_WIDTH [31:0] $end
   $var wire 32 ? ImmOp [31:0] $end
   $var wire 32 D PC [31:0] $end
   $var wire  1 @ PCsrc $end
   $var wire  1 A clk $end
   $var wire 32 C instr [31:0] $end
   $var wire  1 B rst $end
   $scope module myPCreg $end
    $var wire 32 H ADDRESS_WIDTH [31:0] $end
    $var wire 32 ? ImmOp [31:0] $end
    $var wire 32 D PC [31:0] $end
    $var wire  1 @ PCsrc $end
    $var wire 32 E branch_PC [31:0] $end
    $var wire  1 A clk $end
    $var wire 32 F inc_PC [31:0] $end
    $var wire 32 G next_PC [31:0] $end
    $var wire  1 B rst $end
   $upscope $end
   $scope module myRom $end
    $var wire 32 H ADDRESS_WIDTH [31:0] $end
    $var wire 32 I DATA_WIDTH [31:0] $end
    $var wire 32 D PC [31:0] $end
    $var wire 32 C instr [31:0] $end
    $var wire  8 # rom_array[0] [7:0] $end
    $var wire  8 - rom_array[10] [7:0] $end
    $var wire  8 . rom_array[11] [7:0] $end
    $var wire  8 / rom_array[12] [7:0] $end
    $var wire  8 0 rom_array[13] [7:0] $end
    $var wire  8 1 rom_array[14] [7:0] $end
    $var wire  8 2 rom_array[15] [7:0] $end
    $var wire  8 3 rom_array[16] [7:0] $end
    $var wire  8 4 rom_array[17] [7:0] $end
    $var wire  8 5 rom_array[18] [7:0] $end
    $var wire  8 6 rom_array[19] [7:0] $end
    $var wire  8 $ rom_array[1] [7:0] $end
    $var wire  8 7 rom_array[20] [7:0] $end
    $var wire  8 8 rom_array[21] [7:0] $end
    $var wire  8 9 rom_array[22] [7:0] $end
    $var wire  8 : rom_array[23] [7:0] $end
    $var wire  8 ; rom_array[24] [7:0] $end
    $var wire  8 < rom_array[25] [7:0] $end
    $var wire  8 = rom_array[26] [7:0] $end
    $var wire  8 > rom_array[27] [7:0] $end
    $var wire  8 % rom_array[2] [7:0] $end
    $var wire  8 & rom_array[3] [7:0] $end
    $var wire  8 ' rom_array[4] [7:0] $end
    $var wire  8 ( rom_array[5] [7:0] $end
    $var wire  8 ) rom_array[6] [7:0] $end
    $var wire  8 * rom_array[7] [7:0] $end
    $var wire  8 + rom_array[8] [7:0] $end
    $var wire  8 , rom_array[9] [7:0] $end
   $upscope $end
  $upscope $end
 $upscope $end
$enddefinitions $end


#0
b00000000 #
b00000000 $
b00000000 %
b00000000 &
b00000000 '
b00000000 (
b00000000 )
b00000000 *
b00000000 +
b00000000 ,
b00000000 -
b00000000 .
b00000000 /
b00000000 0
b00000000 1
b00000000 2
b00000000 3
b00000000 4
b00000000 5
b00000000 6
b00000000 7
b00000000 8
b00000000 9
b00000000 :
b00000000 ;
b00000000 <
b00000000 =
b00000000 >
b00000000000000000000111111111111 ?
0@
1A
1B
b00000000000000000000000000000000 C
b00000000000000000000000000000000 D
b00000000000000000000111111111111 E
b00000000000000000000000000000100 F
b00000000000000000000000000000100 G
b00000000000000000000000000100000 H
b00000000000000000000000000001000 I
#1
b00001111 #
b11110000 $
b00000011 %
b00010011 &
b00000101 )
b00010011 *
b00000101 -
b10010011 .
b00000101 0
b10000101 1
b00010011 2
b00010101 4
b10000101 5
b10010011 6
b11111110 7
b01100101 8
b10011100 9
b11100011 :
b11111110 ;
b00000011 <
b00011000 =
0A
b00001111111100000000001100010011 C
#2
1A
#3
0A
#4
1A
#5
0A
#6
1A
#7
0A
#8
1A
0B
#9
0A
#10
1A
b00000000000000000000010100010011 C
b00000000000000000000000000000100 D
b00000000000000000001000000000011 E
b00000000000000000000000000001000 F
b00000000000000000000000000001000 G
#11
0A
#12
1A
b00000000000000000000010110010011 C
b00000000000000000000000000001000 D
b00000000000000000001000000000111 E
b00000000000000000000000000001100 F
b00000000000000000000000000001100 G
#13
0A
#14
1A
b00000000000001011000010100010011 C
b00000000000000000000000000001100 D
b00000000000000000001000000001011 E
b00000000000000000000000000010000 F
b00000000000000000000000000010000 G
#15
0A
#16
1A
b00000000000101011000010110010011 C
b00000000000000000000000000010000 D
b00000000000000000001000000001111 E
b00000000000000000000000000010100 F
b00000000000000000000000000010100 G
#17
0A
#18
1A
b11111110011001011001110011100011 C
b00000000000000000000000000010100 D
b00000000000000000001000000010011 E
b00000000000000000000000000011000 F
b00000000000000000000000000011000 G
#19
0A
#20
1A
b11111110000000110001100000000000 C
b00000000000000000000000000011000 D
b00000000000000000001000000010111 E
b00000000000000000000000000011100 F
b00000000000000000000000000011100 G
#21
0A
#22
1A
b00000000000000000000000000000000 C
b00000000000000000000000000011100 D
b00000000000000000001000000011011 E
b00000000000000000000000000100000 F
b00000000000000000000000000100000 G
#23
0A
#24
1A
b00001111111100000000001100010011 C
b00000000000000000000000000100000 D
b00000000000000000001000000011111 E
b00000000000000000000000000100100 F
b00000000000000000000000000100100 G
#25
0A
#26
1A
1B
b00000000000000000000010100010011 C
b00000000000000000000000000100100 D
b00000000000000000001000000100011 E
b00000000000000000000000000101000 F
b00000000000000000000000000101000 G
#27
0A
#28
1A
0B
b00001111111100000000001100010011 C
b00000000000000000000000000000000 D
b00000000000000000000111111111111 E
b00000000000000000000000000000100 F
b00000000000000000000000000000100 G
#29
0A
#30
1A
b00000000000000000000010100010011 C
b00000000000000000000000000000100 D
b00000000000000000001000000000011 E
b00000000000000000000000000001000 F
b00000000000000000000000000001000 G
#31
0A
#32
1A
b00000000000000000000010110010011 C
b00000000000000000000000000001000 D
b00000000000000000001000000000111 E
b00000000000000000000000000001100 F
b00000000000000000000000000001100 G
#33
0A
#34
1A
b00000000000001011000010100010011 C
b00000000000000000000000000001100 D
b00000000000000000001000000001011 E
b00000000000000000000000000010000 F
b00000000000000000000000000010000 G
#35
0A
#36
1A
b00000000000101011000010110010011 C
b00000000000000000000000000010000 D
b00000000000000000001000000001111 E
b00000000000000000000000000010100 F
b00000000000000000000000000010100 G
#37
0A
#38
1A
b11111110011001011001110011100011 C
b00000000000000000000000000010100 D
b00000000000000000001000000010011 E
b00000000000000000000000000011000 F
b00000000000000000000000000011000 G
#39
0A
#40
1A
b11111110000000110001100000000000 C
b00000000000000000000000000011000 D
b00000000000000000001000000010111 E
b00000000000000000000000000011100 F
b00000000000000000000000000011100 G
#41
0A
#42
1A
b00000000000000000000000000000000 C
b00000000000000000000000000011100 D
b00000000000000000001000000011011 E
b00000000000000000000000000100000 F
b00000000000000000000000000100000 G
#43
0A
#44
1A
b00001111111100000000001100010011 C
b00000000000000000000000000100000 D
b00000000000000000001000000011111 E
b00000000000000000000000000100100 F
b00000000000000000000000000100100 G
#45
0A
#46
1A
1B
b00000000000000000000010100010011 C
b00000000000000000000000000100100 D
b00000000000000000001000000100011 E
b00000000000000000000000000101000 F
b00000000000000000000000000101000 G
#47
0A
#48
1A
0B
b00001111111100000000001100010011 C
b00000000000000000000000000000000 D
b00000000000000000000111111111111 E
b00000000000000000000000000000100 F
b00000000000000000000000000000100 G
#49
0A
#50
1A
b00000000000000000000010100010011 C
b00000000000000000000000000000100 D
b00000000000000000001000000000011 E
b00000000000000000000000000001000 F
b00000000000000000000000000001000 G
#51
0A
#52
1A
b00000000000000000000010110010011 C
b00000000000000000000000000001000 D
b00000000000000000001000000000111 E
b00000000000000000000000000001100 F
b00000000000000000000000000001100 G
#53
0A
#54
1A
b00000000000001011000010100010011 C
b00000000000000000000000000001100 D
b00000000000000000001000000001011 E
b00000000000000000000000000010000 F
b00000000000000000000000000010000 G
#55
0A
#56
1A
b00000000000101011000010110010011 C
b00000000000000000000000000010000 D
b00000000000000000001000000001111 E
b00000000000000000000000000010100 F
b00000000000000000000000000010100 G
#57
0A
#58
1A
b11111110011001011001110011100011 C
b00000000000000000000000000010100 D
b00000000000000000001000000010011 E
b00000000000000000000000000011000 F
b00000000000000000000000000011000 G
#59
0A
#60
1A
b11111110000000110001100000000000 C
b00000000000000000000000000011000 D
b00000000000000000001000000010111 E
b00000000000000000000000000011100 F
b00000000000000000000000000011100 G
#61
0A
#62
1A
b00000000000000000000000000000000 C
b00000000000000000000000000011100 D
b00000000000000000001000000011011 E
b00000000000000000000000000100000 F
b00000000000000000000000000100000 G
#63
0A
#64
1A
b00001111111100000000001100010011 C
b00000000000000000000000000100000 D
b00000000000000000001000000011111 E
b00000000000000000000000000100100 F
b00000000000000000000000000100100 G
#65
0A
#66
1A
1B
b00000000000000000000010100010011 C
b00000000000000000000000000100100 D
b00000000000000000001000000100011 E
b00000000000000000000000000101000 F
b00000000000000000000000000101000 G
#67
0A
#68
1A
0B
b00001111111100000000001100010011 C
b00000000000000000000000000000000 D
b00000000000000000000111111111111 E
b00000000000000000000000000000100 F
b00000000000000000000000000000100 G
#69
0A
#70
1A
b00000000000000000000010100010011 C
b00000000000000000000000000000100 D
b00000000000000000001000000000011 E
b00000000000000000000000000001000 F
b00000000000000000000000000001000 G
#71
0A
#72
1A
b00000000000000000000010110010011 C
b00000000000000000000000000001000 D
b00000000000000000001000000000111 E
b00000000000000000000000000001100 F
b00000000000000000000000000001100 G
#73
0A
#74
1A
b00000000000001011000010100010011 C
b00000000000000000000000000001100 D
b00000000000000000001000000001011 E
b00000000000000000000000000010000 F
b00000000000000000000000000010000 G
#75
0A
#76
1A
b00000000000101011000010110010011 C
b00000000000000000000000000010000 D
b00000000000000000001000000001111 E
b00000000000000000000000000010100 F
b00000000000000000000000000010100 G
#77
0A
#78
1A
b11111110011001011001110011100011 C
b00000000000000000000000000010100 D
b00000000000000000001000000010011 E
b00000000000000000000000000011000 F
b00000000000000000000000000011000 G
#79
0A
#80
1A
b11111110000000110001100000000000 C
b00000000000000000000000000011000 D
b00000000000000000001000000010111 E
b00000000000000000000000000011100 F
b00000000000000000000000000011100 G
#81
0A
#82
1A
b00000000000000000000000000000000 C
b00000000000000000000000000011100 D
b00000000000000000001000000011011 E
b00000000000000000000000000100000 F
b00000000000000000000000000100000 G
#83
0A
#84
1A
b00001111111100000000001100010011 C
b00000000000000000000000000100000 D
b00000000000000000001000000011111 E
b00000000000000000000000000100100 F
b00000000000000000000000000100100 G
#85
0A
#86
1A
1B
b00000000000000000000010100010011 C
b00000000000000000000000000100100 D
b00000000000000000001000000100011 E
b00000000000000000000000000101000 F
b00000000000000000000000000101000 G
#87
0A
#88
1A
0B
b00001111111100000000001100010011 C
b00000000000000000000000000000000 D
b00000000000000000000111111111111 E
b00000000000000000000000000000100 F
b00000000000000000000000000000100 G
#89
0A
#90
1A
b00000000000000000000010100010011 C
b00000000000000000000000000000100 D
b00000000000000000001000000000011 E
b00000000000000000000000000001000 F
b00000000000000000000000000001000 G
#91
0A
#92
1A
b00000000000000000000010110010011 C
b00000000000000000000000000001000 D
b00000000000000000001000000000111 E
b00000000000000000000000000001100 F
b00000000000000000000000000001100 G
#93
0A
#94
1A
b00000000000001011000010100010011 C
b00000000000000000000000000001100 D
b00000000000000000001000000001011 E
b00000000000000000000000000010000 F
b00000000000000000000000000010000 G
#95
0A
#96
1A
b00000000000101011000010110010011 C
b00000000000000000000000000010000 D
b00000000000000000001000000001111 E
b00000000000000000000000000010100 F
b00000000000000000000000000010100 G
#97
0A
#98
1A
b11111110011001011001110011100011 C
b00000000000000000000000000010100 D
b00000000000000000001000000010011 E
b00000000000000000000000000011000 F
b00000000000000000000000000011000 G
#99
0A
#100
1A
b11111110000000110001100000000000 C
b00000000000000000000000000011000 D
b00000000000000000001000000010111 E
b00000000000000000000000000011100 F
b00000000000000000000000000011100 G
#101
0A
#102
1A
b00000000000000000000000000000000 C
b00000000000000000000000000011100 D
b00000000000000000001000000011011 E
b00000000000000000000000000100000 F
b00000000000000000000000000100000 G
#103
0A
#104
1A
b00001111111100000000001100010011 C
b00000000000000000000000000100000 D
b00000000000000000001000000011111 E
b00000000000000000000000000100100 F
b00000000000000000000000000100100 G
#105
0A
#106
1A
1B
b00000000000000000000010100010011 C
b00000000000000000000000000100100 D
b00000000000000000001000000100011 E
b00000000000000000000000000101000 F
b00000000000000000000000000101000 G
#107
0A
#108
1A
0B
b00001111111100000000001100010011 C
b00000000000000000000000000000000 D
b00000000000000000000111111111111 E
b00000000000000000000000000000100 F
b00000000000000000000000000000100 G
#109
0A
#110
1A
b00000000000000000000010100010011 C
b00000000000000000000000000000100 D
b00000000000000000001000000000011 E
b00000000000000000000000000001000 F
b00000000000000000000000000001000 G
#111
0A
#112
1A
b00000000000000000000010110010011 C
b00000000000000000000000000001000 D
b00000000000000000001000000000111 E
b00000000000000000000000000001100 F
b00000000000000000000000000001100 G
#113
0A
#114
1A
b00000000000001011000010100010011 C
b00000000000000000000000000001100 D
b00000000000000000001000000001011 E
b00000000000000000000000000010000 F
b00000000000000000000000000010000 G
#115
0A
#116
1A
b00000000000101011000010110010011 C
b00000000000000000000000000010000 D
b00000000000000000001000000001111 E
b00000000000000000000000000010100 F
b00000000000000000000000000010100 G
#117
0A
#118
1A
b11111110011001011001110011100011 C
b00000000000000000000000000010100 D
b00000000000000000001000000010011 E
b00000000000000000000000000011000 F
b00000000000000000000000000011000 G
#119
0A
#120
1A
b11111110000000110001100000000000 C
b00000000000000000000000000011000 D
b00000000000000000001000000010111 E
b00000000000000000000000000011100 F
b00000000000000000000000000011100 G
#121
0A
#122
1A
b00000000000000000000000000000000 C
b00000000000000000000000000011100 D
b00000000000000000001000000011011 E
b00000000000000000000000000100000 F
b00000000000000000000000000100000 G
#123
0A
#124
1A
b00001111111100000000001100010011 C
b00000000000000000000000000100000 D
b00000000000000000001000000011111 E
b00000000000000000000000000100100 F
b00000000000000000000000000100100 G
#125
0A
#126
1A
1B
b00000000000000000000010100010011 C
b00000000000000000000000000100100 D
b00000000000000000001000000100011 E
b00000000000000000000000000101000 F
b00000000000000000000000000101000 G
#127
0A
#128
1A
0B
b00001111111100000000001100010011 C
b00000000000000000000000000000000 D
b00000000000000000000111111111111 E
b00000000000000000000000000000100 F
b00000000000000000000000000000100 G
#129
0A
#130
1A
b00000000000000000000010100010011 C
b00000000000000000000000000000100 D
b00000000000000000001000000000011 E
b00000000000000000000000000001000 F
b00000000000000000000000000001000 G
#131
0A
#132
1A
b00000000000000000000010110010011 C
b00000000000000000000000000001000 D
b00000000000000000001000000000111 E
b00000000000000000000000000001100 F
b00000000000000000000000000001100 G
#133
0A
#134
1A
b00000000000001011000010100010011 C
b00000000000000000000000000001100 D
b00000000000000000001000000001011 E
b00000000000000000000000000010000 F
b00000000000000000000000000010000 G
#135
0A
#136
1A
b00000000000101011000010110010011 C
b00000000000000000000000000010000 D
b00000000000000000001000000001111 E
b00000000000000000000000000010100 F
b00000000000000000000000000010100 G
#137
0A
#138
1A
b11111110011001011001110011100011 C
b00000000000000000000000000010100 D
b00000000000000000001000000010011 E
b00000000000000000000000000011000 F
b00000000000000000000000000011000 G
#139
0A
#140
1A
b11111110000000110001100000000000 C
b00000000000000000000000000011000 D
b00000000000000000001000000010111 E
b00000000000000000000000000011100 F
b00000000000000000000000000011100 G
#141
0A
#142
1A
b00000000000000000000000000000000 C
b00000000000000000000000000011100 D
b00000000000000000001000000011011 E
b00000000000000000000000000100000 F
b00000000000000000000000000100000 G
#143
0A
#144
1A
b00001111111100000000001100010011 C
b00000000000000000000000000100000 D
b00000000000000000001000000011111 E
b00000000000000000000000000100100 F
b00000000000000000000000000100100 G
#145
0A
#146
1A
1B
b00000000000000000000010100010011 C
b00000000000000000000000000100100 D
b00000000000000000001000000100011 E
b00000000000000000000000000101000 F
b00000000000000000000000000101000 G
#147
0A
#148
1A
0B
b00001111111100000000001100010011 C
b00000000000000000000000000000000 D
b00000000000000000000111111111111 E
b00000000000000000000000000000100 F
b00000000000000000000000000000100 G
#149
0A
#150
1A
b00000000000000000000010100010011 C
b00000000000000000000000000000100 D
b00000000000000000001000000000011 E
b00000000000000000000000000001000 F
b00000000000000000000000000001000 G
#151
0A
#152
1A
b00000000000000000000010110010011 C
b00000000000000000000000000001000 D
b00000000000000000001000000000111 E
b00000000000000000000000000001100 F
b00000000000000000000000000001100 G
#153
0A
#154
1A
b00000000000001011000010100010011 C
b00000000000000000000000000001100 D
b00000000000000000001000000001011 E
b00000000000000000000000000010000 F
b00000000000000000000000000010000 G
#155
0A
#156
1A
b00000000000101011000010110010011 C
b00000000000000000000000000010000 D
b00000000000000000001000000001111 E
b00000000000000000000000000010100 F
b00000000000000000000000000010100 G
#157
0A
#158
1A
b11111110011001011001110011100011 C
b00000000000000000000000000010100 D
b00000000000000000001000000010011 E
b00000000000000000000000000011000 F
b00000000000000000000000000011000 G
#159
0A
#160
1A
b11111110000000110001100000000000 C
b00000000000000000000000000011000 D
b00000000000000000001000000010111 E
b00000000000000000000000000011100 F
b00000000000000000000000000011100 G
#161
0A
#162
1A
b00000000000000000000000000000000 C
b00000000000000000000000000011100 D
b00000000000000000001000000011011 E
b00000000000000000000000000100000 F
b00000000000000000000000000100000 G
#163
0A
#164
1A
b00001111111100000000001100010011 C
b00000000000000000000000000100000 D
b00000000000000000001000000011111 E
b00000000000000000000000000100100 F
b00000000000000000000000000100100 G
#165
0A
#166
1A
1B
b00000000000000000000010100010011 C
b00000000000000000000000000100100 D
b00000000000000000001000000100011 E
b00000000000000000000000000101000 F
b00000000000000000000000000101000 G
#167
0A
#168
1A
0B
b00001111111100000000001100010011 C
b00000000000000000000000000000000 D
b00000000000000000000111111111111 E
b00000000000000000000000000000100 F
b00000000000000000000000000000100 G
#169
0A
#170
1A
b00000000000000000000010100010011 C
b00000000000000000000000000000100 D
b00000000000000000001000000000011 E
b00000000000000000000000000001000 F
b00000000000000000000000000001000 G
#171
0A
#172
1A
b00000000000000000000010110010011 C
b00000000000000000000000000001000 D
b00000000000000000001000000000111 E
b00000000000000000000000000001100 F
b00000000000000000000000000001100 G
#173
0A
#174
1A
b00000000000001011000010100010011 C
b00000000000000000000000000001100 D
b00000000000000000001000000001011 E
b00000000000000000000000000010000 F
b00000000000000000000000000010000 G
#175
0A
#176
1A
b00000000000101011000010110010011 C
b00000000000000000000000000010000 D
b00000000000000000001000000001111 E
b00000000000000000000000000010100 F
b00000000000000000000000000010100 G
#177
0A
#178
1A
b11111110011001011001110011100011 C
b00000000000000000000000000010100 D
b00000000000000000001000000010011 E
b00000000000000000000000000011000 F
b00000000000000000000000000011000 G
#179
0A
#180
1A
b11111110000000110001100000000000 C
b00000000000000000000000000011000 D
b00000000000000000001000000010111 E
b00000000000000000000000000011100 F
b00000000000000000000000000011100 G
#181
0A
#182
1A
b00000000000000000000000000000000 C
b00000000000000000000000000011100 D
b00000000000000000001000000011011 E
b00000000000000000000000000100000 F
b00000000000000000000000000100000 G
#183
0A
#184
1A
b00001111111100000000001100010011 C
b00000000000000000000000000100000 D
b00000000000000000001000000011111 E
b00000000000000000000000000100100 F
b00000000000000000000000000100100 G
#185
0A
#186
1A
1B
b00000000000000000000010100010011 C
b00000000000000000000000000100100 D
b00000000000000000001000000100011 E
b00000000000000000000000000101000 F
b00000000000000000000000000101000 G
#187
0A
#188
1A
0B
b00001111111100000000001100010011 C
b00000000000000000000000000000000 D
b00000000000000000000111111111111 E
b00000000000000000000000000000100 F
b00000000000000000000000000000100 G
#189
0A
#190
1A
b00000000000000000000010100010011 C
b00000000000000000000000000000100 D
b00000000000000000001000000000011 E
b00000000000000000000000000001000 F
b00000000000000000000000000001000 G
#191
0A
#192
1A
b00000000000000000000010110010011 C
b00000000000000000000000000001000 D
b00000000000000000001000000000111 E
b00000000000000000000000000001100 F
b00000000000000000000000000001100 G
#193
0A
#194
1A
b00000000000001011000010100010011 C
b00000000000000000000000000001100 D
b00000000000000000001000000001011 E
b00000000000000000000000000010000 F
b00000000000000000000000000010000 G
#195
0A
#196
1A
b00000000000101011000010110010011 C
b00000000000000000000000000010000 D
b00000000000000000001000000001111 E
b00000000000000000000000000010100 F
b00000000000000000000000000010100 G
#197
0A
#198
1A
b11111110011001011001110011100011 C
b00000000000000000000000000010100 D
b00000000000000000001000000010011 E
b00000000000000000000000000011000 F
b00000000000000000000000000011000 G
#199
0A
#200
1A
b11111110000000110001100000000000 C
b00000000000000000000000000011000 D
b00000000000000000001000000010111 E
b00000000000000000000000000011100 F
b00000000000000000000000000011100 G
#201
0A
#202
1A
b00000000000000000000000000000000 C
b00000000000000000000000000011100 D
b00000000000000000001000000011011 E
b00000000000000000000000000100000 F
b00000000000000000000000000100000 G
#203
0A
#204
1A
b00001111111100000000001100010011 C
b00000000000000000000000000100000 D
b00000000000000000001000000011111 E
b00000000000000000000000000100100 F
b00000000000000000000000000100100 G
#205
0A
#206
1A
1B
b00000000000000000000010100010011 C
b00000000000000000000000000100100 D
b00000000000000000001000000100011 E
b00000000000000000000000000101000 F
b00000000000000000000000000101000 G
#207
0A
#208
1A
0B
b00001111111100000000001100010011 C
b00000000000000000000000000000000 D
b00000000000000000000111111111111 E
b00000000000000000000000000000100 F
b00000000000000000000000000000100 G
#209
0A
#210
1A
b00000000000000000000010100010011 C
b00000000000000000000000000000100 D
b00000000000000000001000000000011 E
b00000000000000000000000000001000 F
b00000000000000000000000000001000 G
#211
0A
#212
1A
b00000000000000000000010110010011 C
b00000000000000000000000000001000 D
b00000000000000000001000000000111 E
b00000000000000000000000000001100 F
b00000000000000000000000000001100 G
#213
0A
#214
1A
b00000000000001011000010100010011 C
b00000000000000000000000000001100 D
b00000000000000000001000000001011 E
b00000000000000000000000000010000 F
b00000000000000000000000000010000 G
#215
0A
#216
1A
b00000000000101011000010110010011 C
b00000000000000000000000000010000 D
b00000000000000000001000000001111 E
b00000000000000000000000000010100 F
b00000000000000000000000000010100 G
#217
0A
#218
1A
b11111110011001011001110011100011 C
b00000000000000000000000000010100 D
b00000000000000000001000000010011 E
b00000000000000000000000000011000 F
b00000000000000000000000000011000 G
#219
0A
#220
1A
b11111110000000110001100000000000 C
b00000000000000000000000000011000 D
b00000000000000000001000000010111 E
b00000000000000000000000000011100 F
b00000000000000000000000000011100 G
#221
0A
#222
1A
b00000000000000000000000000000000 C
b00000000000000000000000000011100 D
b00000000000000000001000000011011 E
b00000000000000000000000000100000 F
b00000000000000000000000000100000 G
#223
0A
#224
1A
b00001111111100000000001100010011 C
b00000000000000000000000000100000 D
b00000000000000000001000000011111 E
b00000000000000000000000000100100 F
b00000000000000000000000000100100 G
#225
0A
#226
1A
1B
b00000000000000000000010100010011 C
b00000000000000000000000000100100 D
b00000000000000000001000000100011 E
b00000000000000000000000000101000 F
b00000000000000000000000000101000 G
#227
0A
#228
1A
0B
b00001111111100000000001100010011 C
b00000000000000000000000000000000 D
b00000000000000000000111111111111 E
b00000000000000000000000000000100 F
b00000000000000000000000000000100 G
#229
0A
#230
1A
b00000000000000000000010100010011 C
b00000000000000000000000000000100 D
b00000000000000000001000000000011 E
b00000000000000000000000000001000 F
b00000000000000000000000000001000 G
#231
0A
#232
1A
b00000000000000000000010110010011 C
b00000000000000000000000000001000 D
b00000000000000000001000000000111 E
b00000000000000000000000000001100 F
b00000000000000000000000000001100 G
#233
0A
#234
1A
b00000000000001011000010100010011 C
b00000000000000000000000000001100 D
b00000000000000000001000000001011 E
b00000000000000000000000000010000 F
b00000000000000000000000000010000 G
#235
0A
#236
1A
b00000000000101011000010110010011 C
b00000000000000000000000000010000 D
b00000000000000000001000000001111 E
b00000000000000000000000000010100 F
b00000000000000000000000000010100 G
#237
0A
#238
1A
b11111110011001011001110011100011 C
b00000000000000000000000000010100 D
b00000000000000000001000000010011 E
b00000000000000000000000000011000 F
b00000000000000000000000000011000 G
#239
0A
#240
1A
b11111110000000110001100000000000 C
b00000000000000000000000000011000 D
b00000000000000000001000000010111 E
b00000000000000000000000000011100 F
b00000000000000000000000000011100 G
#241
0A
#242
1A
b00000000000000000000000000000000 C
b00000000000000000000000000011100 D
b00000000000000000001000000011011 E
b00000000000000000000000000100000 F
b00000000000000000000000000100000 G
#243
0A
#244
1A
b00001111111100000000001100010011 C
b00000000000000000000000000100000 D
b00000000000000000001000000011111 E
b00000000000000000000000000100100 F
b00000000000000000000000000100100 G
#245
0A
#246
1A
1B
b00000000000000000000010100010011 C
b00000000000000000000000000100100 D
b00000000000000000001000000100011 E
b00000000000000000000000000101000 F
b00000000000000000000000000101000 G
#247
0A
#248
1A
0B
b00001111111100000000001100010011 C
b00000000000000000000000000000000 D
b00000000000000000000111111111111 E
b00000000000000000000000000000100 F
b00000000000000000000000000000100 G
#249
0A
#250
1A
b00000000000000000000010100010011 C
b00000000000000000000000000000100 D
b00000000000000000001000000000011 E
b00000000000000000000000000001000 F
b00000000000000000000000000001000 G
#251
0A
#252
1A
b00000000000000000000010110010011 C
b00000000000000000000000000001000 D
b00000000000000000001000000000111 E
b00000000000000000000000000001100 F
b00000000000000000000000000001100 G
#253
0A
#254
1A
b00000000000001011000010100010011 C
b00000000000000000000000000001100 D
b00000000000000000001000000001011 E
b00000000000000000000000000010000 F
b00000000000000000000000000010000 G
#255
0A
#256
1A
b00000000000101011000010110010011 C
b00000000000000000000000000010000 D
b00000000000000000001000000001111 E
b00000000000000000000000000010100 F
b00000000000000000000000000010100 G
#257
0A
#258
1A
b11111110011001011001110011100011 C
b00000000000000000000000000010100 D
b00000000000000000001000000010011 E
b00000000000000000000000000011000 F
b00000000000000000000000000011000 G
#259
0A
#260
1A
b11111110000000110001100000000000 C
b00000000000000000000000000011000 D
b00000000000000000001000000010111 E
b00000000000000000000000000011100 F
b00000000000000000000000000011100 G
#261
0A
#262
1A
b00000000000000000000000000000000 C
b00000000000000000000000000011100 D
b00000000000000000001000000011011 E
b00000000000000000000000000100000 F
b00000000000000000000000000100000 G
#263
0A
#264
1A
b00001111111100000000001100010011 C
b00000000000000000000000000100000 D
b00000000000000000001000000011111 E
b00000000000000000000000000100100 F
b00000000000000000000000000100100 G
#265
0A
#266
1A
1B
b00000000000000000000010100010011 C
b00000000000000000000000000100100 D
b00000000000000000001000000100011 E
b00000000000000000000000000101000 F
b00000000000000000000000000101000 G
#267
0A
#268
1A
0B
b00001111111100000000001100010011 C
b00000000000000000000000000000000 D
b00000000000000000000111111111111 E
b00000000000000000000000000000100 F
b00000000000000000000000000000100 G
#269
0A
#270
1A
b00000000000000000000010100010011 C
b00000000000000000000000000000100 D
b00000000000000000001000000000011 E
b00000000000000000000000000001000 F
b00000000000000000000000000001000 G
#271
0A
#272
1A
b00000000000000000000010110010011 C
b00000000000000000000000000001000 D
b00000000000000000001000000000111 E
b00000000000000000000000000001100 F
b00000000000000000000000000001100 G
#273
0A
#274
1A
b00000000000001011000010100010011 C
b00000000000000000000000000001100 D
b00000000000000000001000000001011 E
b00000000000000000000000000010000 F
b00000000000000000000000000010000 G
#275
0A
#276
1A
b00000000000101011000010110010011 C
b00000000000000000000000000010000 D
b00000000000000000001000000001111 E
b00000000000000000000000000010100 F
b00000000000000000000000000010100 G
#277
0A
#278
1A
b11111110011001011001110011100011 C
b00000000000000000000000000010100 D
b00000000000000000001000000010011 E
b00000000000000000000000000011000 F
b00000000000000000000000000011000 G
#279
0A
#280
1A
b11111110000000110001100000000000 C
b00000000000000000000000000011000 D
b00000000000000000001000000010111 E
b00000000000000000000000000011100 F
b00000000000000000000000000011100 G
#281
0A
#282
1A
b00000000000000000000000000000000 C
b00000000000000000000000000011100 D
b00000000000000000001000000011011 E
b00000000000000000000000000100000 F
b00000000000000000000000000100000 G
#283
0A
