PC/rom.sv
module rom #(
    parameter ADDRESS_WIDTH = 8, // loaded 256 instrcutions in rom initially, can increase this, modify mem accordingly.
    DATA_WIDTH = 32 // data width of each instruction has to be 32 to accommodate all possible instructions
)(
    input logic [ADDRESS_WIDTH-1:0] PC,
    output logic [DATA_WIDTH-1:0]   instr
);

logic [DATA_WIDTH-1:0] rom_array [2**ADDRESS_WIDTH-1:0];

initial begin
    $display("Loading rom.");
    $readmemh("instructions.mem", rom_array);
end;


assign instr = rom_array[PC]

endmodule

PC/pcreg.sv
module pcreg #(
    parameter ADDRESS_WIDTH = 8
)(
    // inputs and corresponding outputs from left to right
    input logic [ADDRESS_WIDTH-1:0] ImmOp,
    input logic                     PCsrc,
    input logic                     clk,
    input logic                     rst,
    output logic [ADDRESS_WIDTH-1:0] PC
);

    logic [ADDRESS_WIDTH-1:0] branch_PC;
    logic [ADDRESS_WIDTH-1:0] inc_PC;

initial begin
    PC = {ADDRESS_WIDTH{1'b0}};
end

// intermediate output from the mux block, should be decided based on the value of PCsrc
logic [ADDRESS_WIDTH-1:0] next_PC;

// handles assigning individual control values to the mux block
assign branch_PC = PC + ImmOp;
assign inc_PC = PC + 8'h4;


// handles the mux block
assign next_PC = PCsrc ? branch_PC : inc_PC;

// handles the PC register, note that this part is clocked
always_ff @(posedge clk)
    // synchronous reset
    if(rst) PC <= {ADDRESS_WIDTH{1'b0}};
    else    PC <= next_PC;

endmodule

PC/PC_top.sv
module PC_top #(
        parameter ADDRESS_WIDTH = 8,
        IMMOP_WIDTH = 32, // just a workaround at the moment, will work fine for now but need to figure out why memory allocation isn't taking place accurately.
    DATA_WIDTH = 32
)(
  input logic [IMMOP_WIDTH-1:0] ImmOp,
  input logic                     PCsrc,
  input logic                     clk,
  input logic                     rst,
  output logic [DATA_WIDTH-1:0]   instr
);

  logic [ADDRESS_WIDTH-1:0] PC;
  logic [ADDRESS_WIDTH-1:0] ImmOp_intermed;

  assign ImmOp_intermed = ImmOp[ADDRESS_WIDTH-1:0];

pcreg myPCreg (
  .ImmOp(ImmOp_intermed),
  .PC(PC),
  .PCsrc(PCsrc),
  .clk (clk),
  .rst (rst)
);

rom myRom (
  .PC(PC),
  .instr(instr)
);

endmodule

PC/PC_top.vcd
$version Generated by VerilatedVcd $end
$date Fri Nov 25 10:19:40 2022 $end
$timescale 1ps $end

 $scope module TOP $end
  $var wire 32 # ImmOp [31:0] $end
  $var wire  1 $ PCsrc $end
  $var wire  1 % clk $end
  $var wire 32 ' instr [31:0] $end
  $var wire  1 & rst $end
  $scope module PC_top $end
   $var wire 32 - ADDRESS_WIDTH [31:0] $end
   $var wire 32 . DATA_WIDTH [31:0] $end
   $var wire 32 . IMMOP_WIDTH [31:0] $end
   $var wire 32 # ImmOp [31:0] $end
   $var wire  8 ) ImmOp_intermed [7:0] $end
   $var wire  8 ( PC [7:0] $end
   $var wire  1 $ PCsrc $end
   $var wire  1 % clk $end
   $var wire 32 ' instr [31:0] $end
   $var wire  1 & rst $end
   $scope module myPCreg $end
    $var wire 32 - ADDRESS_WIDTH [31:0] $end
    $var wire  8 ) ImmOp [7:0] $end
    $var wire  8 ( PC [7:0] $end
    $var wire  1 $ PCsrc $end
    $var wire  8 * branch_PC [7:0] $end
    $var wire  1 % clk $end
    $var wire  8 + inc_PC [7:0] $end
    $var wire  8 , next_PC [7:0] $end
    $var wire  1 & rst $end
   $upscope $end
   $scope module myRom $end
    $var wire 32 - ADDRESS_WIDTH [31:0] $end
    $var wire 32 . DATA_WIDTH [31:0] $end
    $var wire  8 ( PC [7:0] $end
    $var wire 32 ' instr [31:0] $end
   $upscope $end
  $upscope $end
 $upscope $end
$enddefinitions $end


#0
b00000000000000000000111111111111 #
0$
1%
1&
b00000000000000000000000000000000 '
b00000000 (
b11111111 )
b11111111 *
b00000100 +
b00000100 ,
b00000000000000000000000000001000 -
b00000000000000000000000000100000 .
#1
0%
b00001111111100000000001100010011 '
#2
1%
#3
0%
#4
1%
#5
0%
#6
1%
#7
0%
#8
1%
0&
#9
0%
#10
1%
b00000000000000000000010100010011 '
b00000100 (
b00000011 *
b00001000 +
b00001000 ,
#11
0%
#12
1%
b00000000000000000000010110010011 '
b00001000 (
b00000111 *
b00001100 +
b00001100 ,
#13
0%
#14
1%
b00000000000001011000010100010011 '
b00001100 (
b00001011 *
b00010000 +
b00010000 ,
#15
0%
#16
1%
b00000000000101011000010110010011 '
b00010000 (
b00001111 *
b00010100 +
b00010100 ,
#17
0%
#18
1%
b11111110011001011001110011100011 '
b00010100 (
b00010011 *
b00011000 +
b00011000 ,
#19
0%
#20
1%
b11111110000000110001100011100011 '
b00011000 (
b00010111 *
b00011100 +
b00011100 ,
#21
0%
#22
1%
b00000000000000000000000000000000 '
b00011100 (
b00011011 *
b00100000 +
b00100000 ,
#23
0%
#24
1%
b00100000 (
b00011111 *
b00100100 +
b00100100 ,
#25
0%
#26
1%
1&
b00100100 (
b00100011 *
b00101000 +
b00101000 ,
#27
0%
#28
1%
0&
b00001111111100000000001100010011 '
b00000000 (
b11111111 *
b00000100 +
b00000100 ,
#29
0%
#30
1%
b00000000000000000000010100010011 '
b00000100 (
b00000011 *
b00001000 +
b00001000 ,
#31
0%
#32
1%
b00000000000000000000010110010011 '
b00001000 (
b00000111 *
b00001100 +
b00001100 ,
#33
0%
#34
1%
b00000000000001011000010100010011 '
b00001100 (
b00001011 *
b00010000 +
b00010000 ,
#35
0%
#36
1%
b00000000000101011000010110010011 '
b00010000 (
b00001111 *
b00010100 +
b00010100 ,
#37
0%
#38
1%
b11111110011001011001110011100011 '
b00010100 (
b00010011 *
b00011000 +
b00011000 ,
#39
0%
#40
1%
b11111110000000110001100011100011 '
b00011000 (
b00010111 *
b00011100 +
b00011100 ,
#41
0%
#42
1%
b00000000000000000000000000000000 '
b00011100 (
b00011011 *
b00100000 +
b00100000 ,
#43
0%
#44
1%
b00100000 (
b00011111 *
b00100100 +
b00100100 ,
#45
0%
#46
1%
1&
b00100100 (
b00100011 *
b00101000 +
b00101000 ,
#47
0%
#48
1%
0&
b00001111111100000000001100010011 '
b00000000 (
b11111111 *
b00000100 +
b00000100 ,
#49
0%
#50
1%
b00000000000000000000010100010011 '
b00000100 (
b00000011 *
b00001000 +
b00001000 ,
#51
0%
#52
1%
b00000000000000000000010110010011 '
b00001000 (
b00000111 *
b00001100 +
b00001100 ,
#53
0%
#54
1%
b00000000000001011000010100010011 '
b00001100 (
b00001011 *
b00010000 +
b00010000 ,
#55
0%
#56
1%
b00000000000101011000010110010011 '
b00010000 (
b00001111 *
b00010100 +
b00010100 ,
#57
0%
#58
1%
b11111110011001011001110011100011 '
b00010100 (
b00010011 *
b00011000 +
b00011000 ,
#59
0%
#60
1%
b11111110000000110001100011100011 '
b00011000 (
b00010111 *
b00011100 +
b00011100 ,
#61
0%
#62
1%
b00000000000000000000000000000000 '
b00011100 (
b00011011 *
b00100000 +
b00100000 ,
#63
0%
#64
1%
b00100000 (
b00011111 *
b00100100 +
b00100100 ,
#65
0%
#66
1%
1&
b00100100 (
b00100011 *
b00101000 +
b00101000 ,
#67
0%
#68
1%
0&
b00001111111100000000001100010011 '
b00000000 (
b11111111 *
b00000100 +
b00000100 ,
#69
0%
#70
1%
b00000000000000000000010100010011 '
b00000100 (
b00000011 *
b00001000 +
b00001000 ,
#71
0%
#72
1%
b00000000000000000000010110010011 '
b00001000 (
b00000111 *
b00001100 +
b00001100 ,
#73
0%
#74
1%
b00000000000001011000010100010011 '
b00001100 (
b00001011 *
b00010000 +
b00010000 ,
#75
0%
#76
1%
b00000000000101011000010110010011 '
b00010000 (
b00001111 *
b00010100 +
b00010100 ,
#77
0%
#78
1%
b11111110011001011001110011100011 '
b00010100 (
b00010011 *
b00011000 +
b00011000 ,
#79
0%
#80
1%
b11111110000000110001100011100011 '
b00011000 (
b00010111 *
b00011100 +
b00011100 ,
#81
0%
#82
1%
b00000000000000000000000000000000 '
b00011100 (
b00011011 *
b00100000 +
b00100000 ,
#83
0%
#84
1%
b00100000 (
b00011111 *
b00100100 +
b00100100 ,
#85
0%
#86
1%
1&
b00100100 (
b00100011 *
b00101000 +
b00101000 ,
#87
0%
#88
1%
0&
b00001111111100000000001100010011 '
b00000000 (
b11111111 *
b00000100 +
b00000100 ,
#89
0%
#90
1%
b00000000000000000000010100010011 '
b00000100 (
b00000011 *
b00001000 +
b00001000 ,
#91
0%
#92
1%
b00000000000000000000010110010011 '
b00001000 (
b00000111 *
b00001100 +
b00001100 ,
#93
0%
#94
1%
b00000000000001011000010100010011 '
b00001100 (
b00001011 *
b00010000 +
b00010000 ,
#95
0%
#96
1%
b00000000000101011000010110010011 '
b00010000 (
b00001111 *
b00010100 +
b00010100 ,
#97
0%
#98
1%
b11111110011001011001110011100011 '
b00010100 (
b00010011 *
b00011000 +
b00011000 ,
#99
0%
#100
1%
b11111110000000110001100011100011 '
b00011000 (
b00010111 *
b00011100 +
b00011100 ,
#101
0%
#102
1%
b00000000000000000000000000000000 '
b00011100 (
b00011011 *
b00100000 +
b00100000 ,
#103
0%
#104
1%
b00100000 (
b00011111 *
b00100100 +
b00100100 ,
#105
0%
#106
1%
1&
b00100100 (
b00100011 *
b00101000 +
b00101000 ,
#107
0%
#108
1%
0&
b00001111111100000000001100010011 '
b00000000 (
b11111111 *
b00000100 +
b00000100 ,
#109
0%
#110
1%
b00000000000000000000010100010011 '
b00000100 (
b00000011 *
b00001000 +
b00001000 ,
#111
0%
#112
1%
b00000000000000000000010110010011 '
b00001000 (
b00000111 *
b00001100 +
b00001100 ,
#113
0%
#114
1%
b00000000000001011000010100010011 '
b00001100 (
b00001011 *
b00010000 +
b00010000 ,
#115
0%
#116
1%
b00000000000101011000010110010011 '
b00010000 (
b00001111 *
b00010100 +
b00010100 ,
#117
0%
#118
1%
b11111110011001011001110011100011 '
b00010100 (
b00010011 *
b00011000 +
b00011000 ,
#119
0%
#120
1%
b11111110000000110001100011100011 '
b00011000 (
b00010111 *
b00011100 +
b00011100 ,
#121
0%
#122
1%
b00000000000000000000000000000000 '
b00011100 (
b00011011 *
b00100000 +
b00100000 ,
#123
0%
#124
1%
b00100000 (
b00011111 *
b00100100 +
b00100100 ,
#125
0%
#126
1%
1&
b00100100 (
b00100011 *
b00101000 +
b00101000 ,
#127
0%
#128
1%
0&
b00001111111100000000001100010011 '
b00000000 (
b11111111 *
b00000100 +
b00000100 ,
#129
0%
#130
1%
b00000000000000000000010100010011 '
b00000100 (
b00000011 *
b00001000 +
b00001000 ,
#131
0%
#132
1%
b00000000000000000000010110010011 '
b00001000 (
b00000111 *
b00001100 +
b00001100 ,
#133
0%
#134
1%
b00000000000001011000010100010011 '
b00001100 (
b00001011 *
b00010000 +
b00010000 ,
#135
0%
#136
1%
b00000000000101011000010110010011 '
b00010000 (
b00001111 *
b00010100 +
b00010100 ,
#137
0%
#138
1%
b11111110011001011001110011100011 '
b00010100 (
b00010011 *
b00011000 +
b00011000 ,
#139
0%
#140
1%
b11111110000000110001100011100011 '
b00011000 (
b00010111 *
b00011100 +
b00011100 ,
#141
0%
#142
1%
b00000000000000000000000000000000 '
b00011100 (
b00011011 *
b00100000 +
b00100000 ,
#143
0%
#144
1%
b00100000 (
b00011111 *
b00100100 +
b00100100 ,
#145
0%
#146
1%
1&
b00100100 (
b00100011 *
b00101000 +
b00101000 ,
#147
0%
#148
1%
0&
b00001111111100000000001100010011 '
b00000000 (
b11111111 *
b00000100 +
b00000100 ,
#149
0%
#150
1%
b00000000000000000000010100010011 '
b00000100 (
b00000011 *
b00001000 +
b00001000 ,
#151
0%
#152
1%
b00000000000000000000010110010011 '
b00001000 (
b00000111 *
b00001100 +
b00001100 ,
#153
0%
#154
1%
b00000000000001011000010100010011 '
b00001100 (
b00001011 *
b00010000 +
b00010000 ,
#155
0%
#156
1%
b00000000000101011000010110010011 '
b00010000 (
b00001111 *
b00010100 +
b00010100 ,
#157
0%
#158
1%
b11111110011001011001110011100011 '
b00010100 (
b00010011 *
b00011000 +
b00011000 ,
#159
0%
#160
1%
b11111110000000110001100011100011 '
b00011000 (
b00010111 *
b00011100 +
b00011100 ,
#161
0%
#162
1%
b00000000000000000000000000000000 '
b00011100 (
b00011011 *
b00100000 +
b00100000 ,
#163
0%
#164
1%
b00100000 (
b00011111 *
b00100100 +
b00100100 ,
#165
0%
#166
1%
1&
b00100100 (
b00100011 *
b00101000 +
b00101000 ,
#167
0%
#168
1%
0&
b00001111111100000000001100010011 '
b00000000 (
b11111111 *
b00000100 +
b00000100 ,
#169
0%
#170
1%
b00000000000000000000010100010011 '
b00000100 (
b00000011 *
b00001000 +
b00001000 ,
#171
0%
#172
1%
b00000000000000000000010110010011 '
b00001000 (
b00000111 *
b00001100 +
b00001100 ,
#173
0%
#174
1%
b00000000000001011000010100010011 '
b00001100 (
b00001011 *
b00010000 +
b00010000 ,
#175
0%
#176
1%
b00000000000101011000010110010011 '
b00010000 (
b00001111 *
b00010100 +
b00010100 ,
#177
0%
#178
1%
b11111110011001011001110011100011 '
b00010100 (
b00010011 *
b00011000 +
b00011000 ,
#179
0%
#180
1%
b11111110000000110001100011100011 '
b00011000 (
b00010111 *
b00011100 +
b00011100 ,
#181
0%
#182
1%
b00000000000000000000000000000000 '
b00011100 (
b00011011 *
b00100000 +
b00100000 ,
#183
0%
#184
1%
b00100000 (
b00011111 *
b00100100 +
b00100100 ,
#185
0%
#186
1%
1&
b00100100 (
b00100011 *
b00101000 +
b00101000 ,
#187
0%
#188
1%
0&
b00001111111100000000001100010011 '
b00000000 (
b11111111 *
b00000100 +
b00000100 ,
#189
0%
#190
1%
b00000000000000000000010100010011 '
b00000100 (
b00000011 *
b00001000 +
b00001000 ,
#191
0%
#192
1%
b00000000000000000000010110010011 '
b00001000 (
b00000111 *
b00001100 +
b00001100 ,
#193
0%
#194
1%
b00000000000001011000010100010011 '
b00001100 (
b00001011 *
b00010000 +
b00010000 ,
#195
0%
#196
1%
b00000000000101011000010110010011 '
b00010000 (
b00001111 *
b00010100 +
b00010100 ,
#197
0%
#198
1%
b11111110011001011001110011100011 '
b00010100 (
b00010011 *
b00011000 +
b00011000 ,
#199
0%
#200
1%
b11111110000000110001100011100011 '
b00011000 (
b00010111 *
b00011100 +
b00011100 ,
#201
0%
#202
1%
b00000000000000000000000000000000 '
b00011100 (
b00011011 *
b00100000 +
b00100000 ,
#203
0%
#204
1%
b00100000 (
b00011111 *
b00100100 +
b00100100 ,
#205
0%
#206
1%
1&
b00100100 (
b00100011 *
b00101000 +
b00101000 ,
#207
0%
#208
1%
0&
b00001111111100000000001100010011 '
b00000000 (
b11111111 *
b00000100 +
b00000100 ,
#209
0%
#210
1%
b00000000000000000000010100010011 '
b00000100 (
b00000011 *
b00001000 +
b00001000 ,
#211
0%
#212
1%
b00000000000000000000010110010011 '
b00001000 (
b00000111 *
b00001100 +
b00001100 ,
#213
0%
#214
1%
b00000000000001011000010100010011 '
b00001100 (
b00001011 *
b00010000 +
b00010000 ,
#215
0%
#216
1%
b00000000000101011000010110010011 '
b00010000 (
b00001111 *
b00010100 +
b00010100 ,
#217
0%
#218
1%
b11111110011001011001110011100011 '
b00010100 (
b00010011 *
b00011000 +
b00011000 ,
#219
0%
#220
1%
b11111110000000110001100011100011 '
b00011000 (
b00010111 *
b00011100 +
b00011100 ,
#221
0%
#222
1%
b00000000000000000000000000000000 '
b00011100 (
b00011011 *
b00100000 +
b00100000 ,
#223
0%
#224
1%
b00100000 (
b00011111 *
b00100100 +
b00100100 ,
#225
0%
#226
1%
1&
b00100100 (
b00100011 *
b00101000 +
b00101000 ,
#227
0%
#228
1%
0&
b00001111111100000000001100010011 '
b00000000 (
b11111111 *
b00000100 +
b00000100 ,
#229
0%
#230
1%
b00000000000000000000010100010011 '
b00000100 (
b00000011 *
b00001000 +
b00001000 ,
#231
0%
#232
1%
b00000000000000000000010110010011 '
b00001000 (
b00000111 *
b00001100 +
b00001100 ,
#233
0%
#234
1%
b00000000000001011000010100010011 '
b00001100 (
b00001011 *
b00010000 +
b00010000 ,
#235
0%
#236
1%
b00000000000101011000010110010011 '
b00010000 (
b00001111 *
b00010100 +
b00010100 ,
#237
0%
#238
1%
b11111110011001011001110011100011 '
b00010100 (
b00010011 *
b00011000 +
b00011000 ,
#239
0%
#240
1%
b11111110000000110001100011100011 '
b00011000 (
b00010111 *
b00011100 +
b00011100 ,
#241
0%
#242
1%
b00000000000000000000000000000000 '
b00011100 (
b00011011 *
b00100000 +
b00100000 ,
#243
0%
#244
1%
b00100000 (
b00011111 *
b00100100 +
b00100100 ,
#245
0%
#246
1%
1&
b00100100 (
b00100011 *
b00101000 +
b00101000 ,
#247
0%
#248
1%
0&
b00001111111100000000001100010011 '
b00000000 (
b11111111 *
b00000100 +
b00000100 ,
#249
0%
#250
1%
b00000000000000000000010100010011 '
b00000100 (
b00000011 *
b00001000 +
b00001000 ,
#251
0%
#252
1%
b00000000000000000000010110010011 '
b00001000 (
b00000111 *
b00001100 +
b00001100 ,
#253
0%
#254
1%
b00000000000001011000010100010011 '
b00001100 (
b00001011 *
b00010000 +
b00010000 ,
#255
0%
#256
1%
b00000000000101011000010110010011 '
b00010000 (
b00001111 *
b00010100 +
b00010100 ,
#257
0%
#258
1%
b11111110011001011001110011100011 '
b00010100 (
b00010011 *
b00011000 +
b00011000 ,
#259
0%
#260
1%
b11111110000000110001100011100011 '
b00011000 (
b00010111 *
b00011100 +
b00011100 ,
#261
0%
#262
1%
b00000000000000000000000000000000 '
b00011100 (
b00011011 *
b00100000 +
b00100000 ,
#263
0%
#264
1%
b00100000 (
b00011111 *
b00100100 +
b00100100 ,
#265
0%
#266
1%
1&
b00100100 (
b00100011 *
b00101000 +
b00101000 ,
#267
0%
#268
1%
0&
b00001111111100000000001100010011 '
b00000000 (
b11111111 *
b00000100 +
b00000100 ,
#269
0%
#270
1%
b00000000000000000000010100010011 '
b00000100 (
b00000011 *
b00001000 +
b00001000 ,
#271
0%
#272
1%
b00000000000000000000010110010011 '
b00001000 (
b00000111 *
b00001100 +
b00001100 ,
#273
0%
#274
1%
b00000000000001011000010100010011 '
b00001100 (
b00001011 *
b00010000 +
b00010000 ,
#275
0%
#276
1%
b00000000000101011000010110010011 '
b00010000 (
b00001111 *
b00010100 +
b00010100 ,
#277
0%
#278
1%
b11111110011001011001110011100011 '
b00010100 (
b00010011 *
b00011000 +
b00011000 ,
#279
0%
#280
1%
b11111110000000110001100011100011 '
b00011000 (
b00010111 *
b00011100 +
b00011100 ,
#281
0%
#282
1%
b00000000000000000000000000000000 '
b00011100 (
b00011011 *
b00100000 +
b00100000 ,
#283
0%
#284
1%
b00100000 (
b00011111 *
b00100100 +
b00100100 ,
#285
0%
#286
1%
1&
b00100100 (
b00100011 *
b00101000 +
b00101000 ,
#287
0%
#288
1%
0&
b00001111111100000000001100010011 '
b00000000 (
b11111111 *
b00000100 +
b00000100 ,
#289
0%
#290
1%
b00000000000000000000010100010011 '
b00000100 (
b00000011 *
b00001000 +
b00001000 ,
#291
0%
#292
1%
b00000000000000000000010110010011 '
b00001000 (
b00000111 *
b00001100 +
b00001100 ,
#293
0%
#294
1%
b00000000000001011000010100010011 '
b00001100 (
b00001011 *
b00010000 +
b00010000 ,
#295
0%
#296
1%
b00000000000101011000010110010011 '
b00010000 (
b00001111 *
b00010100 +
b00010100 ,
#297
0%
#298
1%
b11111110011001011001110011100011 '
b00010100 (
b00010011 *
b00011000 +
b00011000 ,
#299
0%
#300
1%
b11111110000000110001100011100011 '
b00011000 (
b00010111 *
b00011100 +
b00011100 ,
#301
0%
#302
1%
b00000000000000000000000000000000 '
b00011100 (
b00011011 *
b00100000 +
b00100000 ,
#303
0%
#304
1%
b00100000 (
b00011111 *
b00100100 +
b00100100 ,
#305
0%
#306
1%
1&
b00100100 (
b00100011 *
b00101000 +
b00101000 ,
#307
0%
#308
1%
0&
b00001111111100000000001100010011 '
b00000000 (
b11111111 *
b00000100 +
b00000100 ,
#309
0%
#310
1%
b00000000000000000000010100010011 '
b00000100 (
b00000011 *
b00001000 +
b00001000 ,
#311
0%
#312
1%
b00000000000000000000010110010011 '
b00001000 (
b00000111 *
b00001100 +
b00001100 ,
#313
0%
#314
1%
b00000000000001011000010100010011 '
b00001100 (
b00001011 *
b00010000 +
b00010000 ,
#315
0%
#316
1%
b00000000000101011000010110010011 '
b00010000 (
b00001111 *
b00010100 +
b00010100 ,
#317
0%
#318
1%
b11111110011001011001110011100011 '
b00010100 (
b00010011 *
b00011000 +
b00011000 ,
#319
0%
#320
1%
b11111110000000110001100011100011 '
b00011000 (
b00010111 *
b00011100 +
b00011100 ,
#321
0%
#322
1%
b00000000000000000000000000000000 '
b00011100 (
b00011011 *
b00100000 +
b00100000 ,
#323
0%
#324
1%
b00100000 (
b00011111 *
b00100100 +
b00100100 ,
#325
0%
#326
1%
1&
b00100100 (
b00100011 *
b00101000 +
b00101000 ,
#327
0%
#328
1%
0&
b00001111111100000000001100010011 '
b00000000 (
b11111111 *
b00000100 +
b00000100 ,
#329
0%
#330
1%
b00000000000000000000010100010011 '
b00000100 (
b00000011 *
b00001000 +
b00001000 ,
#331
0%
#332
1%
b00000000000000000000010110010011 '
b00001000 (
b00000111 *
b00001100 +
b00001100 ,
#333
0%
#334
1%
b00000000000001011000010100010011 '
b00001100 (
b00001011 *
b00010000 +
b00010000 ,
#335
0%
#336
1%
b00000000000101011000010110010011 '
b00010000 (
b00001111 *
b00010100 +
b00010100 ,
#337
0%
#338
1%
b11111110011001011001110011100011 '
b00010100 (
b00010011 *
b00011000 +
b00011000 ,
#339
0%
#340
1%
b11111110000000110001100011100011 '
b00011000 (
b00010111 *
b00011100 +
b00011100 ,
#341
0%
#342
1%
b00000000000000000000000000000000 '
b00011100 (
b00011011 *
b00100000 +
b00100000 ,
#343
0%
#344
1%
b00100000 (
b00011111 *
b00100100 +
b00100100 ,
#345
0%
#346
1%
1&
b00100100 (
b00100011 *
b00101000 +
b00101000 ,
#347
0%
#348
1%
0&
b00001111111100000000001100010011 '
b00000000 (
b11111111 *
b00000100 +
b00000100 ,
#349
0%
#350
1%
b00000000000000000000010100010011 '
b00000100 (
b00000011 *
b00001000 +
b00001000 ,
#351
0%
#352
1%
b00000000000000000000010110010011 '
b00001000 (
b00000111 *
b00001100 +
b00001100 ,
#353
0%
#354
1%
b00000000000001011000010100010011 '
b00001100 (
b00001011 *
b00010000 +
b00010000 ,
#355
0%
#356
1%
b00000000000101011000010110010011 '
b00010000 (
b00001111 *
b00010100 +
b00010100 ,
#357
0%
#358
1%
b11111110011001011001110011100011 '
b00010100 (
b00010011 *
b00011000 +
b00011000 ,
#359
0%
#360
1%
b11111110000000110001100011100011 '
b00011000 (
b00010111 *
b00011100 +
b00011100 ,
#361
0%
#362
1%
b00000000000000000000000000000000 '
b00011100 (
b00011011 *
b00100000 +
b00100000 ,
#363
0%
#364
1%
b00100000 (
b00011111 *
b00100100 +
b00100100 ,
#365
0%
#366
1%
1&
b00100100 (
b00100011 *
b00101000 +
b00101000 ,
#367
0%
#368
1%
0&
b00001111111100000000001100010011 '
b00000000 (
b11111111 *
b00000100 +
b00000100 ,
#369
0%
#370
1%
b00000000000000000000010100010011 '
b00000100 (
b00000011 *
b00001000 +
b00001000 ,
#371
0%
#372
1%
b00000000000000000000010110010011 '
b00001000 (
b00000111 *
b00001100 +
b00001100 ,
#373
0%
#374
1%
b00000000000001011000010100010011 '
b00001100 (
b00001011 *
b00010000 +
b00010000 ,
#375
0%
#376
1%
b00000000000101011000010110010011 '
b00010000 (
b00001111 *
b00010100 +
b00010100 ,
#377
0%
#378
1%
b11111110011001011001110011100011 '
b00010100 (
b00010011 *
b00011000 +
b00011000 ,
#379
0%
#380
1%
b11111110000000110001100011100011 '
b00011000 (
b00010111 *
b00011100 +
b00011100 ,
#381
0%
#382
1%
b00000000000000000000000000000000 '
b00011100 (
b00011011 *
b00100000 +
b00100000 ,
#383
0%
#384
1%
b00100000 (
b00011111 *
b00100100 +
b00100100 ,
#385
0%
#386
1%
1&
b00100100 (
b00100011 *
b00101000 +
b00101000 ,
#387
0%
#388
1%
0&
b00001111111100000000001100010011 '
b00000000 (
b11111111 *
b00000100 +
b00000100 ,
#389
0%
#390
1%
b00000000000000000000010100010011 '
b00000100 (
b00000011 *
b00001000 +
b00001000 ,
#391
0%
#392
1%
b00000000000000000000010110010011 '
b00001000 (
b00000111 *
b00001100 +
b00001100 ,
#393
0%
#394
1%
b00000000000001011000010100010011 '
b00001100 (
b00001011 *
b00010000 +
b00010000 ,
#395
0%
#396
1%
b00000000000101011000010110010011 '
b00010000 (
b00001111 *
b00010100 +
b00010100 ,
#397
0%
#398
1%
b11111110011001011001110011100011 '
b00010100 (
b00010011 *
b00011000 +
b00011000 ,
#399
0%
#400
1%
b11111110000000110001100011100011 '
b00011000 (
b00010111 *
b00011100 +
b00011100 ,
#401
0%
#402
1%
b00000000000000000000000000000000 '
b00011100 (
b00011011 *
b00100000 +
b00100000 ,
#403
0%
#404
1%
b00100000 (
b00011111 *
b00100100 +
b00100100 ,
#405
0%
#406
1%
1&
b00100100 (
b00100011 *
b00101000 +
b00101000 ,
#407
0%
#408
1%
0&
b00001111111100000000001100010011 '
b00000000 (
b11111111 *
b00000100 +
b00000100 ,
#409
0%
#410
1%
b00000000000000000000010100010011 '
b00000100 (
b00000011 *
b00001000 +
b00001000 ,
#411
0%
#412
1%
b00000000000000000000010110010011 '
b00001000 (
b00000111 *
b00001100 +
b00001100 ,
#413
0%
#414
1%
b00000000000001011000010100010011 '
b00001100 (
b00001011 *
b00010000 +
b00010000 ,
#415
0%
#416
1%
b00000000000101011000010110010011 '
b00010000 (
b00001111 *
b00010100 +
b00010100 ,
#417
0%
#418
1%
b11111110011001011001110011100011 '
b00010100 (
b00010011 *
b00011000 +
b00011000 ,
#419
0%
#420
1%
b11111110000000110001100011100011 '
b00011000 (
b00010111 *
b00011100 +
b00011100 ,
#421
0%
#422
1%
b00000000000000000000000000000000 '
b00011100 (
b00011011 *
b00100000 +
b00100000 ,
#423
0%
#424
1%
b00100000 (
b00011111 *
b00100100 +
b00100100 ,
#425
0%
#426
1%
1&
b00100100 (
b00100011 *
b00101000 +
b00101000 ,
#427
0%
#428
1%
0&
b00001111111100000000001100010011 '
b00000000 (
b11111111 *
b00000100 +
b00000100 ,
#429
0%
#430
1%
b00000000000000000000010100010011 '
b00000100 (
b00000011 *
b00001000 +
b00001000 ,
#431
0%
#432
1%
b00000000000000000000010110010011 '
b00001000 (
b00000111 *
b00001100 +
b00001100 ,
#433
0%
#434
1%
b00000000000001011000010100010011 '
b00001100 (
b00001011 *
b00010000 +
b00010000 ,
#435
0%
#436
1%
b00000000000101011000010110010011 '
b00010000 (
b00001111 *
b00010100 +
b00010100 ,
#437
0%
#438
1%
b11111110011001011001110011100011 '
b00010100 (
b00010011 *
b00011000 +
b00011000 ,
#439
0%
#440
1%
b11111110000000110001100011100011 '
b00011000 (
b00010111 *
b00011100 +
b00011100 ,
#441
0%
#442
1%
b00000000000000000000000000000000 '
b00011100 (
b00011011 *
b00100000 +
b00100000 ,
#443
0%
#444
1%
b00100000 (
b00011111 *
b00100100 +
b00100100 ,
#445
0%
#446
1%
1&
b00100100 (
b00100011 *
b00101000 +
b00101000 ,
#447
0%
#448
1%
0&
b00001111111100000000001100010011 '
b00000000 (
b11111111 *
b00000100 +
b00000100 ,
#449
0%
#450
1%
b00000000000000000000010100010011 '
b00000100 (
b00000011 *
b00001000 +
b00001000 ,
#451
0%
#452
1%
b00000000000000000000010110010011 '
b00001000 (
b00000111 *
b00001100 +
b00001100 ,
#453
0%
#454
1%
b00000000000001011000010100010011 '
b00001100 (
b00001011 *
b00010000 +
b00010000 ,
#455
0%
#456
1%
b00000000000101011000010110010011 '
b00010000 (
b00001111 *
b00010100 +
b00010100 ,
#457
0%
#458
1%
b11111110011001011001110011100011 '
b00010100 (
b00010011 *
b00011000 +
b00011000 ,
#459
0%
#460
1%
b11111110000000110001100011100011 '
b00011000 (
b00010111 *
b00011100 +
b00011100 ,
#461
0%
#462
1%
b00000000000000000000000000000000 '
b00011100 (
b00011011 *
b00100000 +
b00100000 ,
#463
0%
#464
1%
b00100000 (
b00011111 *
b00100100 +
b00100100 ,
#465
0%
#466
1%
1&
b00100100 (
b00100011 *
b00101000 +
b00101000 ,
#467
0%
#468
1%
0&
b00001111111100000000001100010011 '
b00000000 (
b11111111 *
b00000100 +
b00000100 ,
#469
0%
#470
1%
b00000000000000000000010100010011 '
b00000100 (
b00000011 *
b00001000 +
b00001000 ,
#471
0%
#472
1%
b00000000000000000000010110010011 '
b00001000 (
b00000111 *
b00001100 +
b00001100 ,
#473
0%
#474
1%
b00000000000001011000010100010011 '
b00001100 (
b00001011 *
b00010000 +
b00010000 ,
#475
0%
#476
1%
b00000000000101011000010110010011 '
b00010000 (
b00001111 *
b00010100 +
b00010100 ,
#477
0%
#478
1%
b11111110011001011001110011100011 '
b00010100 (
b00010011 *
b00011000 +
b00011000 ,
#479
0%
#480
1%
b11111110000000110001100011100011 '
b00011000 (
b00010111 *
b00011100 +
b00011100 ,
#481
0%
#482
1%
b00000000000000000000000000000000 '
b00011100 (
b00011011 *
b00100000 +
b00100000 ,
#483
0%
#484
1%
b00100000 (
b00011111 *
b00100100 +
b00100100 ,
#485
0%
#486
1%
1&
b00100100 (
b00100011 *
b00101000 +
b00101000 ,
#487
0%
#488
1%
0&
b00001111111100000000001100010011 '
b00000000 (
b11111111 *
b00000100 +
b00000100 ,
#489
0%
#490
1%
b00000000000000000000010100010011 '
b00000100 (
b00000011 *
b00001000 +
b00001000 ,
#491
0%
