PC/rom.sv
module rom #(
    parameter ADDRESS_WIDTH = 8,// should be 32 bits but having some trouble accommodating memory.
    DATA_WIDTH = 32 // data width of each instruction has to be 32 to accommodate all possible instructions
)(
    input logic [ADDRESS_WIDTH-1:0] PC,
    output logic [DATA_WIDTH-1:0]   instr
);

logic [DATA_WIDTH-1:0] rom_array [2**ADDRESS_WIDTH-1:0];

initial begin
    $display("Loading rom.");
    $readmemh("instructions.mem", rom_array);
    $display("Rom successfully loaded.");
end;

// asynchronous assignment, should be blocking
assign instr = rom_array[PC];

endmodule

PC/pcreg.sv
module pcreg #(
    parameter ADDRESS_WIDTH = 8
)(
    // inputs and corresponding outputs from left to right
    input logic [ADDRESS_WIDTH-1:0] ImmOp,
    input logic                     PCsrc,
    input logic                     clk,
    input logic                     rst,
    output logic [ADDRESS_WIDTH-1:0] PC
);

    logic [ADDRESS_WIDTH-1:0] branch_PC;
    logic [ADDRESS_WIDTH-1:0] inc_PC;

initial begin
    PC = {ADDRESS_WIDTH{1'b0}};
end

// intermediate output from the mux block, should be decided based on the value of PCsrc
logic [ADDRESS_WIDTH-1:0] next_PC;

// handles assigning individual control values to the mux block
assign branch_PC = PC + ImmOp;
assign inc_PC = PC + 8'h4;


// handles the mux block
assign next_PC = PCsrc ? branch_PC : inc_PC;

// handles the PC register, note that this part is clocked
always_ff @(posedge clk)
    // synchronous reset
    if(rst) PC <= {ADDRESS_WIDTH{1'b0}};
    else    PC <= next_PC;

endmodule

PC/PC_top.sv
module PC_top #(
        parameter ADDRESS_WIDTH = 8,
        IMMOP_WIDTH = 32, // just a workaround at the moment, will work fine for now but need to figure out why memory alloation isn't taking place accurately.
    DATA_WIDTH = 32
)(
  input logic [IMMOP_WIDTH-1:0] ImmOp,
  input logic                     PCsrc,
  input logic                     clk,
  input logic                     rst,
  output logic [DATA_WIDTH-1:0]   instr
);

  logic [ADDRESS_WIDTH-1:0] PC;
  logic [ADDRESS_WIDTH-1:0] ImmOp_intermed;

  assign ImmOp_intermed = ImmOp[ADDRESS_WIDTH-1:0];

pcreg myPCreg (
  .ImmOp(ImmOp_intermed),
  .PC(PC),
  .PCsrc(PCsrc),
  .clk (clk),
  .rst (rst)
);

rom myRom (
  .PC(PC),
  .instr(instr)
);

endmodule

PC/PC_top.vcd
$version Generated by VerilatedVcd $end
$date Tue Nov 22 12:39:35 2022 $end
$timescale 1ps $end

 $scope module TOP $end
  $var wire 32 # ImmOp [31:0] $end
  $var wire  1 $ PCsrc $end
  $var wire  1 % clk $end
  $var wire 32 ' instr [31:0] $end
  $var wire  1 & rst $end
  $scope module PC_top $end
   $var wire 32 - ADDRESS_WIDTH [31:0] $end
   $var wire 32 . DATA_WIDTH [31:0] $end
   $var wire 32 . IMMOP_WIDTH [31:0] $end
   $var wire 32 # ImmOp [31:0] $end
   $var wire  8 ) ImmOp_intermed [7:0] $end
   $var wire  8 ( PC [7:0] $end
   $var wire  1 $ PCsrc $end
   $var wire  1 % clk $end
   $var wire 32 ' instr [31:0] $end
   $var wire  1 & rst $end
   $scope module myPCreg $end
    $var wire 32 - ADDRESS_WIDTH [31:0] $end
    $var wire  8 ) ImmOp [7:0] $end
    $var wire  8 ( PC [7:0] $end
    $var wire  1 $ PCsrc $end
    $var wire  8 * branch_PC [7:0] $end
    $var wire  1 % clk $end
    $var wire  8 + inc_PC [7:0] $end
    $var wire  8 , next_PC [7:0] $end
    $var wire  1 & rst $end
   $upscope $end
   $scope module myRom $end
    $var wire 32 - ADDRESS_WIDTH [31:0] $end
    $var wire 32 . DATA_WIDTH [31:0] $end
    $var wire  8 ( PC [7:0] $end
    $var wire 32 ' instr [31:0] $end
   $upscope $end
  $upscope $end
 $upscope $end
$enddefinitions $end


#0
b00000000000000000000111111111111 #
1$
1%
1&
b00000000000000000000000000000000 '
b00000000 (
b11111111 )
b11111111 *
b00000100 +
b11111111 ,
b00000000000000000000000000001000 -
b00000000000000000000000000100000 .
#1
0%
b00001111111100000000001100010011 '
#2
1%
#3
0%
#4
1%
0&
#5
0%
#6
1%
b00000000000000000000000000000000 '
b11111111 (
b11111110 *
b00000011 +
b11111110 ,
#7
0%
#8
1%
b11111110 (
b11111101 *
b00000010 +
b11111101 ,
#9
0%
#10
1%
b11111101 (
b11111100 *
b00000001 +
b11111100 ,
#11
0%
#12
1%
b11111100 (
b11111011 *
b00000000 +
b11111011 ,
#13
0%
#14
1%
b11111011 (
b11111010 *
b11111111 +
b11111010 ,
#15
0%
#16
1%
b11111010 (
b11111001 *
b11111110 +
b11111001 ,
#17
0%
#18
1%
b11111001 (
b11111000 *
b11111101 +
b11111000 ,
#19
0%
#20
1%
b11111000 (
b11110111 *
b11111100 +
b11110111 ,
#21
0%
#22
1%
b11110111 (
b11110110 *
b11111011 +
b11110110 ,
#23
0%
#24
1%
b11110110 (
b11110101 *
b11111010 +
b11110101 ,
#25
0%
#26
1%
1&
b11110101 (
b11110100 *
b11111001 +
b11110100 ,
#27
0%
#28
1%
0&
b00001111111100000000001100010011 '
b00000000 (
b11111111 *
b00000100 +
b11111111 ,
#29
0%
#30
1%
b00000000000000000000000000000000 '
b11111111 (
b11111110 *
b00000011 +
b11111110 ,
#31
0%
#32
1%
b11111110 (
b11111101 *
b00000010 +
b11111101 ,
#33
0%
#34
1%
b11111101 (
b11111100 *
b00000001 +
b11111100 ,
#35
0%
#36
1%
b11111100 (
b11111011 *
b00000000 +
b11111011 ,
#37
0%
#38
1%
b11111011 (
b11111010 *
b11111111 +
b11111010 ,
#39
0%
#40
1%
b11111010 (
b11111001 *
b11111110 +
b11111001 ,
#41
0%
#42
1%
b11111001 (
b11111000 *
b11111101 +
b11111000 ,
#43
0%
#44
1%
b11111000 (
b11110111 *
b11111100 +
b11110111 ,
#45
0%
#46
1%
b11110111 (
b11110110 *
b11111011 +
b11110110 ,
#47
0%
#48
1%
b11110110 (
b11110101 *
b11111010 +
b11110101 ,
#49
0%
#50
1%
1&
b11110101 (
b11110100 *
b11111001 +
b11110100 ,
#51
0%
#52
1%
0&
b00001111111100000000001100010011 '
b00000000 (
b11111111 *
b00000100 +
b11111111 ,
#53
0%
#54
1%
b00000000000000000000000000000000 '
b11111111 (
b11111110 *
b00000011 +
b11111110 ,
#55
0%
#56
1%
b11111110 (
b11111101 *
b00000010 +
b11111101 ,
#57
0%
#58
1%
b11111101 (
b11111100 *
b00000001 +
b11111100 ,
#59
0%
#60
1%
b11111100 (
b11111011 *
b00000000 +
b11111011 ,
#61
0%
#62
1%
b11111011 (
b11111010 *
b11111111 +
b11111010 ,
#63
0%
#64
1%
b11111010 (
b11111001 *
b11111110 +
b11111001 ,
#65
0%
#66
1%
b11111001 (
b11111000 *
b11111101 +
b11111000 ,
#67
0%
#68
1%
b11111000 (
b11110111 *
b11111100 +
b11110111 ,
#69
0%
#70
1%
b11110111 (
b11110110 *
b11111011 +
b11110110 ,
#71
0%
#72
1%
b11110110 (
b11110101 *
b11111010 +
b11110101 ,
#73
0%
#74
1%
1&
b11110101 (
b11110100 *
b11111001 +
b11110100 ,
#75
0%
#76
1%
0&
b00001111111100000000001100010011 '
b00000000 (
b11111111 *
b00000100 +
b11111111 ,
#77
0%
#78
1%
b00000000000000000000000000000000 '
b11111111 (
b11111110 *
b00000011 +
b11111110 ,
#79
0%
#80
1%
b11111110 (
b11111101 *
b00000010 +
b11111101 ,
#81
0%
#82
1%
b11111101 (
b11111100 *
b00000001 +
b11111100 ,
#83
0%
#84
1%
b11111100 (
b11111011 *
b00000000 +
b11111011 ,
#85
0%
#86
1%
b11111011 (
b11111010 *
b11111111 +
b11111010 ,
#87
0%
#88
1%
b11111010 (
b11111001 *
b11111110 +
b11111001 ,
#89
0%
#90
1%
b11111001 (
b11111000 *
b11111101 +
b11111000 ,
#91
0%
#92
1%
b11111000 (
b11110111 *
b11111100 +
b11110111 ,
#93
0%
#94
1%
b11110111 (
b11110110 *
b11111011 +
b11110110 ,
#95
0%
#96
1%
b11110110 (
b11110101 *
b11111010 +
b11110101 ,
#97
0%
#98
1%
1&
b11110101 (
b11110100 *
b11111001 +
b11110100 ,
#99
0%
#100
1%
0&
b00001111111100000000001100010011 '
b00000000 (
b11111111 *
b00000100 +
b11111111 ,
#101
0%
#102
1%
b00000000000000000000000000000000 '
b11111111 (
b11111110 *
b00000011 +
b11111110 ,
#103
0%
#104
1%
b11111110 (
b11111101 *
b00000010 +
b11111101 ,
#105
0%
#106
1%
b11111101 (
b11111100 *
b00000001 +
b11111100 ,
#107
0%
#108
1%
b11111100 (
b11111011 *
b00000000 +
b11111011 ,
#109
0%
#110
1%
b11111011 (
b11111010 *
b11111111 +
b11111010 ,
#111
0%
#112
1%
b11111010 (
b11111001 *
b11111110 +
b11111001 ,
#113
0%
#114
1%
b11111001 (
b11111000 *
b11111101 +
b11111000 ,
#115
0%
#116
1%
b11111000 (
b11110111 *
b11111100 +
b11110111 ,
#117
0%
#118
1%
b11110111 (
b11110110 *
b11111011 +
b11110110 ,
#119
0%
#120
1%
b11110110 (
b11110101 *
b11111010 +
b11110101 ,
#121
0%
#122
1%
1&
b11110101 (
b11110100 *
b11111001 +
b11110100 ,
#123
0%
#124
1%
0&
b00001111111100000000001100010011 '
b00000000 (
b11111111 *
b00000100 +
b11111111 ,
#125
0%
#126
1%
b00000000000000000000000000000000 '
b11111111 (
b11111110 *
b00000011 +
b11111110 ,
#127
0%
#128
1%
b11111110 (
b11111101 *
b00000010 +
b11111101 ,
#129
0%
#130
1%
b11111101 (
b11111100 *
b00000001 +
b11111100 ,
#131
0%
#132
1%
b11111100 (
b11111011 *
b00000000 +
b11111011 ,
#133
0%
#134
1%
b11111011 (
b11111010 *
b11111111 +
b11111010 ,
#135
0%
#136
1%
b11111010 (
b11111001 *
b11111110 +
b11111001 ,
#137
0%
#138
1%
b11111001 (
b11111000 *
b11111101 +
b11111000 ,
#139
0%
#140
1%
b11111000 (
b11110111 *
b11111100 +
b11110111 ,
#141
0%
#142
1%
b11110111 (
b11110110 *
b11111011 +
b11110110 ,
#143
0%
#144
1%
b11110110 (
b11110101 *
b11111010 +
b11110101 ,
#145
0%
#146
1%
1&
b11110101 (
b11110100 *
b11111001 +
b11110100 ,
#147
0%
#148
1%
0&
b00001111111100000000001100010011 '
b00000000 (
b11111111 *
b00000100 +
b11111111 ,
#149
0%
#150
1%
b00000000000000000000000000000000 '
b11111111 (
b11111110 *
b00000011 +
b11111110 ,
#151
0%
#152
1%
b11111110 (
b11111101 *
b00000010 +
b11111101 ,
#153
0%
#154
1%
b11111101 (
b11111100 *
b00000001 +
b11111100 ,
#155
0%
#156
1%
b11111100 (
b11111011 *
b00000000 +
b11111011 ,
#157
0%
#158
1%
b11111011 (
b11111010 *
b11111111 +
b11111010 ,
#159
0%
#160
1%
b11111010 (
b11111001 *
b11111110 +
b11111001 ,
#161
0%
#162
1%
b11111001 (
b11111000 *
b11111101 +
b11111000 ,
#163
0%
#164
1%
b11111000 (
b11110111 *
b11111100 +
b11110111 ,
#165
0%
#166
1%
b11110111 (
b11110110 *
b11111011 +
b11110110 ,
#167
0%
#168
1%
b11110110 (
b11110101 *
b11111010 +
b11110101 ,
#169
0%
#170
1%
1&
b11110101 (
b11110100 *
b11111001 +
b11110100 ,
#171
0%
#172
1%
0&
b00001111111100000000001100010011 '
b00000000 (
b11111111 *
b00000100 +
b11111111 ,
#173
0%
#174
1%
b00000000000000000000000000000000 '
b11111111 (
b11111110 *
b00000011 +
b11111110 ,
#175
0%
#176
1%
b11111110 (
b11111101 *
b00000010 +
b11111101 ,
#177
0%
#178
1%
b11111101 (
b11111100 *
b00000001 +
b11111100 ,
#179
0%
#180
1%
b11111100 (
b11111011 *
b00000000 +
b11111011 ,
#181
0%
#182
1%
b11111011 (
b11111010 *
b11111111 +
b11111010 ,
#183
0%
#184
1%
b11111010 (
b11111001 *
b11111110 +
b11111001 ,
#185
0%
#186
1%
b11111001 (
b11111000 *
b11111101 +
b11111000 ,
#187
0%
#188
1%
b11111000 (
b11110111 *
b11111100 +
b11110111 ,
#189
0%
#190
1%
b11110111 (
b11110110 *
b11111011 +
b11110110 ,
#191
0%
#192
1%
b11110110 (
b11110101 *
b11111010 +
b11110101 ,
#193
0%
#194
1%
1&
b11110101 (
b11110100 *
b11111001 +
b11110100 ,
#195
0%
#196
1%
0&
b00001111111100000000001100010011 '
b00000000 (
b11111111 *
b00000100 +
b11111111 ,
#197
0%
#198
1%
b00000000000000000000000000000000 '
b11111111 (
b11111110 *
b00000011 +
b11111110 ,
#199
0%
#200
1%
b11111110 (
b11111101 *
b00000010 +
b11111101 ,
#201
0%
#202
1%
b11111101 (
b11111100 *
b00000001 +
b11111100 ,
#203
0%
#204
1%
b11111100 (
b11111011 *
b00000000 +
b11111011 ,
#205
0%
#206
1%
b11111011 (
b11111010 *
b11111111 +
b11111010 ,
#207
0%
#208
1%
b11111010 (
b11111001 *
b11111110 +
b11111001 ,
#209
0%
#210
1%
b11111001 (
b11111000 *
b11111101 +
b11111000 ,
#211
0%
#212
1%
b11111000 (
b11110111 *
b11111100 +
b11110111 ,
#213
0%
#214
1%
b11110111 (
b11110110 *
b11111011 +
b11110110 ,
#215
0%
#216
1%
b11110110 (
b11110101 *
b11111010 +
b11110101 ,
#217
0%
#218
1%
1&
b11110101 (
b11110100 *
b11111001 +
b11110100 ,
#219
0%
#220
1%
0&
b00001111111100000000001100010011 '
b00000000 (
b11111111 *
b00000100 +
b11111111 ,
#221
0%
#222
1%
b00000000000000000000000000000000 '
b11111111 (
b11111110 *
b00000011 +
b11111110 ,
#223
0%
#224
1%
b11111110 (
b11111101 *
b00000010 +
b11111101 ,
#225
0%
#226
1%
b11111101 (
b11111100 *
b00000001 +
b11111100 ,
#227
0%
#228
1%
b11111100 (
b11111011 *
b00000000 +
b11111011 ,
#229
0%
#230
1%
b11111011 (
b11111010 *
b11111111 +
b11111010 ,
#231
0%
#232
1%
b11111010 (
b11111001 *
b11111110 +
b11111001 ,
#233
0%
#234
1%
b11111001 (
b11111000 *
b11111101 +
b11111000 ,
#235
0%
#236
1%
b11111000 (
b11110111 *
b11111100 +
b11110111 ,
#237
0%
#238
1%
b11110111 (
b11110110 *
b11111011 +
b11110110 ,
#239
0%
#240
1%
b11110110 (
b11110101 *
b11111010 +
b11110101 ,
#241
0%
#242
1%
1&
b11110101 (
b11110100 *
b11111001 +
b11110100 ,
#243
0%
#244
1%
0&
b00001111111100000000001100010011 '
b00000000 (
b11111111 *
b00000100 +
b11111111 ,
#245
0%
#246
1%
b00000000000000000000000000000000 '
b11111111 (
b11111110 *
b00000011 +
b11111110 ,
#247
0%
#248
1%
b11111110 (
b11111101 *
b00000010 +
b11111101 ,
#249
0%
#250
1%
b11111101 (
b11111100 *
b00000001 +
b11111100 ,
#251
0%
#252
1%
b11111100 (
b11111011 *
b00000000 +
b11111011 ,
#253
0%
#254
1%
b11111011 (
b11111010 *
b11111111 +
b11111010 ,
#255
0%
#256
1%
b11111010 (
b11111001 *
b11111110 +
b11111001 ,
#257
0%
#258
1%
b11111001 (
b11111000 *
b11111101 +
b11111000 ,
#259
0%
#260
1%
b11111000 (
b11110111 *
b11111100 +
b11110111 ,
#261
0%
#262
1%
b11110111 (
b11110110 *
b11111011 +
b11110110 ,
#263
0%
#264
1%
b11110110 (
b11110101 *
b11111010 +
b11110101 ,
#265
0%
#266
1%
1&
b11110101 (
b11110100 *
b11111001 +
b11110100 ,
#267
0%
#268
1%
0&
b00001111111100000000001100010011 '
b00000000 (
b11111111 *
b00000100 +
b11111111 ,
#269
0%
#270
1%
b00000000000000000000000000000000 '
b11111111 (
b11111110 *
b00000011 +
b11111110 ,
#271
0%
#272
1%
b11111110 (
b11111101 *
b00000010 +
b11111101 ,
#273
0%
#274
1%
b11111101 (
b11111100 *
b00000001 +
b11111100 ,
#275
0%
#276
1%
b11111100 (
b11111011 *
b00000000 +
b11111011 ,
#277
0%
#278
1%
b11111011 (
b11111010 *
b11111111 +
b11111010 ,
#279
0%
#280
1%
b11111010 (
b11111001 *
b11111110 +
b11111001 ,
#281
0%
#282
1%
b11111001 (
b11111000 *
b11111101 +
b11111000 ,
#283
0%
#284
1%
b11111000 (
b11110111 *
b11111100 +
b11110111 ,
#285
0%
#286
1%
b11110111 (
b11110110 *
b11111011 +
b11110110 ,
#287
0%
#288
1%
b11110110 (
b11110101 *
b11111010 +
b11110101 ,
#289
0%
#290
1%
1&
b11110101 (
b11110100 *
b11111001 +
b11110100 ,
#291
0%
#292
1%
0&
b00001111111100000000001100010011 '
b00000000 (
b11111111 *
b00000100 +
b11111111 ,
#293
0%
#294
1%
b00000000000000000000000000000000 '
b11111111 (
b11111110 *
b00000011 +
b11111110 ,
#295
0%
#296
1%
b11111110 (
b11111101 *
b00000010 +
b11111101 ,
#297
0%
#298
1%
b11111101 (
b11111100 *
b00000001 +
b11111100 ,
#299
0%
#300
1%
b11111100 (
b11111011 *
b00000000 +
b11111011 ,
#301
0%
#302
1%
b11111011 (
b11111010 *
b11111111 +
b11111010 ,
#303
0%
#304
1%
b11111010 (
b11111001 *
b11111110 +
b11111001 ,
#305
0%
#306
1%
b11111001 (
b11111000 *
b11111101 +
b11111000 ,
#307
0%
#308
1%
b11111000 (
b11110111 *
b11111100 +
b11110111 ,
#309
0%
#310
1%
b11110111 (
b11110110 *
b11111011 +
b11110110 ,
#311
0%
#312
1%
b11110110 (
b11110101 *
b11111010 +
b11110101 ,
#313
0%
#314
1%
1&
b11110101 (
b11110100 *
b11111001 +
b11110100 ,
#315
0%
#316
1%
0&
b00001111111100000000001100010011 '
b00000000 (
b11111111 *
b00000100 +
b11111111 ,
#317
0%
#318
1%
b00000000000000000000000000000000 '
b11111111 (
b11111110 *
b00000011 +
b11111110 ,
#319
0%
#320
1%
b11111110 (
b11111101 *
b00000010 +
b11111101 ,
#321
0%
#322
1%
b11111101 (
b11111100 *
b00000001 +
b11111100 ,
#323
0%
#324
1%
b11111100 (
b11111011 *
b00000000 +
b11111011 ,
#325
0%
#326
1%
b11111011 (
b11111010 *
b11111111 +
b11111010 ,
#327
0%
#328
1%
b11111010 (
b11111001 *
b11111110 +
b11111001 ,
#329
0%
#330
1%
b11111001 (
b11111000 *
b11111101 +
b11111000 ,
#331
0%
#332
1%
b11111000 (
b11110111 *
b11111100 +
b11110111 ,
#333
0%
#334
1%
b11110111 (
b11110110 *
b11111011 +
b11110110 ,
#335
0%
#336
1%
b11110110 (
b11110101 *
b11111010 +
b11110101 ,
#337
0%
#338
1%
1&
b11110101 (
b11110100 *
b11111001 +
b11110100 ,
#339
0%
#340
1%
0&
b00001111111100000000001100010011 '
b00000000 (
b11111111 *
b00000100 +
b11111111 ,
#341
0%
#342
1%
b00000000000000000000000000000000 '
b11111111 (
b11111110 *
b00000011 +
b11111110 ,
#343
0%
#344
1%
b11111110 (
b11111101 *
b00000010 +
b11111101 ,
#345
0%
#346
1%
b11111101 (
b11111100 *
b00000001 +
b11111100 ,
#347
0%
#348
1%
b11111100 (
b11111011 *
b00000000 +
b11111011 ,
#349
0%
#350
1%
b11111011 (
b11111010 *
b11111111 +
b11111010 ,
#351
0%
#352
1%
b11111010 (
b11111001 *
b11111110 +
b11111001 ,
#353
0%
#354
1%
b11111001 (
b11111000 *
b11111101 +
b11111000 ,
#355
0%
#356
1%
b11111000 (
b11110111 *
b11111100 +
b11110111 ,
#357
0%
#358
1%
b11110111 (
b11110110 *
b11111011 +
b11110110 ,
#359
0%
#360
1%
b11110110 (
b11110101 *
b11111010 +
b11110101 ,
#361
0%
#362
1%
1&
b11110101 (
b11110100 *
b11111001 +
b11110100 ,
#363
0%
#364
1%
0&
b00001111111100000000001100010011 '
b00000000 (
b11111111 *
b00000100 +
b11111111 ,
#365
0%
#366
1%
b00000000000000000000000000000000 '
b11111111 (
b11111110 *
b00000011 +
b11111110 ,
#367
0%
#368
1%
b11111110 (
b11111101 *
b00000010 +
b11111101 ,
#369
0%
#370
1%
b11111101 (
b11111100 *
b00000001 +
b11111100 ,
#371
0%
#372
1%
b11111100 (
b11111011 *
b00000000 +
b11111011 ,
#373
0%
#374
1%
b11111011 (
b11111010 *
b11111111 +
b11111010 ,
#375
0%
#376
1%
b11111010 (
b11111001 *
b11111110 +
b11111001 ,
#377
0%
#378
1%
b11111001 (
b11111000 *
b11111101 +
b11111000 ,
#379
0%
#380
1%
b11111000 (
b11110111 *
b11111100 +
b11110111 ,
#381
0%
#382
1%
b11110111 (
b11110110 *
b11111011 +
b11110110 ,
#383
0%
#384
1%
b11110110 (
b11110101 *
b11111010 +
b11110101 ,
#385
0%
#386
1%
1&
b11110101 (
b11110100 *
b11111001 +
b11110100 ,
#387
0%
#388
1%
0&
b00001111111100000000001100010011 '
b00000000 (
b11111111 *
b00000100 +
b11111111 ,
#389
0%
#390
1%
b00000000000000000000000000000000 '
b11111111 (
b11111110 *
b00000011 +
b11111110 ,
#391
0%
#392
1%
b11111110 (
b11111101 *
b00000010 +
b11111101 ,
#393
0%
#394
1%
b11111101 (
b11111100 *
b00000001 +
b11111100 ,
#395
0%
#396
1%
b11111100 (
b11111011 *
b00000000 +
b11111011 ,
#397
0%
#398
1%
b11111011 (
b11111010 *
b11111111 +
b11111010 ,
#399
0%
#400
1%
b11111010 (
b11111001 *
b11111110 +
b11111001 ,
#401
0%
#402
1%
b11111001 (
b11111000 *
b11111101 +
b11111000 ,
#403
0%
#404
1%
b11111000 (
b11110111 *
b11111100 +
b11110111 ,
#405
0%
#406
1%
b11110111 (
b11110110 *
b11111011 +
b11110110 ,
#407
0%
#408
1%
b11110110 (
b11110101 *
b11111010 +
b11110101 ,
#409
0%
#410
1%
1&
b11110101 (
b11110100 *
b11111001 +
b11110100 ,
#411
0%
#412
1%
0&
b00001111111100000000001100010011 '
b00000000 (
b11111111 *
b00000100 +
b11111111 ,
#413
0%
#414
1%
b00000000000000000000000000000000 '
b11111111 (
b11111110 *
b00000011 +
b11111110 ,
#415
0%
#416
1%
b11111110 (
b11111101 *
b00000010 +
b11111101 ,
#417
0%
#418
1%
b11111101 (
b11111100 *
b00000001 +
b11111100 ,
#419
0%
#420
1%
b11111100 (
b11111011 *
b00000000 +
b11111011 ,
#421
0%
#422
1%
b11111011 (
b11111010 *
b11111111 +
b11111010 ,
#423
0%
#424
1%
b11111010 (
b11111001 *
b11111110 +
b11111001 ,
#425
0%
#426
1%
b11111001 (
b11111000 *
b11111101 +
b11111000 ,
#427
0%
#428
1%
b11111000 (
b11110111 *
b11111100 +
b11110111 ,
#429
0%
#430
1%
b11110111 (
b11110110 *
b11111011 +
b11110110 ,
#431
0%
#432
1%
b11110110 (
b11110101 *
b11111010 +
b11110101 ,
#433
0%
#434
1%
1&
b11110101 (
b11110100 *
b11111001 +
b11110100 ,
#435
0%
#436
1%
0&
b00001111111100000000001100010011 '
b00000000 (
b11111111 *
b00000100 +
b11111111 ,
#437
0%
#438
1%
b00000000000000000000000000000000 '
b11111111 (
b11111110 *
b00000011 +
b11111110 ,
#439
0%
#440
1%
b11111110 (
b11111101 *
b00000010 +
b11111101 ,
#441
0%
#442
1%
b11111101 (
b11111100 *
b00000001 +
b11111100 ,
#443
0%
#444
1%
b11111100 (
b11111011 *
b00000000 +
b11111011 ,
#445
0%
#446
1%
b11111011 (
b11111010 *
b11111111 +
b11111010 ,
#447
0%
#448
1%
b11111010 (
b11111001 *
b11111110 +
b11111001 ,
#449
0%
#450
1%
b11111001 (
b11111000 *
b11111101 +
b11111000 ,
#451
0%
#452
1%
b11111000 (
b11110111 *
b11111100 +
b11110111 ,
#453
0%
#454
1%
b11110111 (
b11110110 *
b11111011 +
b11110110 ,
#455
0%
#456
1%
b11110110 (
b11110101 *
b11111010 +
b11110101 ,
#457
0%
#458
1%
1&
b11110101 (
b11110100 *
b11111001 +
b11110100 ,
#459
0%
#460
1%
0&
b00001111111100000000001100010011 '
b00000000 (
b11111111 *
b00000100 +
b11111111 ,
#461
0%
#462
1%
b00000000000000000000000000000000 '
b11111111 (
b11111110 *
b00000011 +
b11111110 ,
#463
0%
#464
1%
b11111110 (
b11111101 *
b00000010 +
b11111101 ,
#465
0%
#466
1%
b11111101 (
b11111100 *
b00000001 +
b11111100 ,
#467
0%
#468
1%
b11111100 (
b11111011 *
b00000000 +
b11111011 ,
#469
0%
#470
1%
b11111011 (
b11111010 *
b11111111 +
b11111010 ,
#471
0%
#472
1%
b11111010 (
b11111001 *
b11111110 +
b11111001 ,
#473
0%
#474
1%
b11111001 (
b11111000 *
b11111101 +
b11111000 ,
#475
0%
#476
1%
b11111000 (
b11110111 *
b11111100 +
b11110111 ,
#477
0%
#478
1%
b11110111 (
b11110110 *
b11111011 +
b11110110 ,
#479
0%
#480
1%
b11110110 (
b11110101 *
b11111010 +
b11110101 ,
#481
0%
#482
1%
1&
b11110101 (
b11110100 *
b11111001 +
b11110100 ,
#483
0%
#484
1%
0&
b00001111111100000000001100010011 '
b00000000 (
b11111111 *
b00000100 +
b11111111 ,
#485
0%
#486
1%
b00000000000000000000000000000000 '
b11111111 (
b11111110 *
b00000011 +
b11111110 ,
#487
0%
#488
1%
b11111110 (
b11111101 *
b00000010 +
b11111101 ,
#489
0%
#490
1%
b11111101 (
b11111100 *
b00000001 +
b11111100 ,
#491
0%
#492
1%
b11111100 (
b11111011 *
b00000000 +
b11111011 ,
#493
0%
#494
1%
b11111011 (
b11111010 *
b11111111 +
b11111010 ,
#495
0%
#496
1%
b11111010 (
b11111001 *
b11111110 +
b11111001 ,
#497
0%
#498
1%
b11111001 (
b11111000 *
b11111101 +
b11111000 ,
#499
0%
#500
1%
b11111000 (
b11110111 *
b11111100 +
b11110111 ,
#501
0%
#502
1%
b11110111 (
b11110110 *
b11111011 +
b11110110 ,
#503
0%
#504
1%
b11110110 (
b11110101 *
b11111010 +
b11110101 ,
#505
0%
#506
1%
1&
b11110101 (
b11110100 *
b11111001 +
b11110100 ,
#507
0%
#508
1%
0&
b00001111111100000000001100010011 '
b00000000 (
b11111111 *
b00000100 +
b11111111 ,
#509
0%
#510
1%
b00000000000000000000000000000000 '
b11111111 (
b11111110 *
b00000011 +
b11111110 ,
#511
0%
#512
1%
b11111110 (
b11111101 *
b00000010 +
b11111101 ,
#513
0%
#514
1%
b11111101 (
b11111100 *
b00000001 +
b11111100 ,
#515
0%
#516
1%
b11111100 (
b11111011 *
b00000000 +
b11111011 ,
#517
0%
#518
1%
b11111011 (
b11111010 *
b11111111 +
b11111010 ,
#519
0%
#520
1%
b11111010 (
b11111001 *
b11111110 +
b11111001 ,
#521
0%
#522
1%
b11111001 (
b11111000 *
b11111101 +
b11111000 ,
#523
0%
#524
1%
b11111000 (
b11110111 *
b11111100 +
b11110111 ,
#525
0%
#526
1%
b11110111 (
b11110110 *
b11111011 +
b11110110 ,
#527
0%
#528
1%
b11110110 (
b11110101 *
b11111010 +
b11110101 ,
#529
0%
#530
1%
1&
b11110101 (
b11110100 *
b11111001 +
b11110100 ,
#531
0%
#532
1%
0&
b00001111111100000000001100010011 '
b00000000 (
b11111111 *
b00000100 +
b11111111 ,
#533
0%
#534
1%
b00000000000000000000000000000000 '
b11111111 (
b11111110 *
b00000011 +
b11111110 ,
#535
0%
#536
1%
b11111110 (
b11111101 *
b00000010 +
b11111101 ,
#537
0%
#538
1%
b11111101 (
b11111100 *
b00000001 +
b11111100 ,
#539
0%
#540
1%
b11111100 (
b11111011 *
b00000000 +
b11111011 ,
#541
0%
#542
1%
b11111011 (
b11111010 *
b11111111 +
b11111010 ,
#543
0%
#544
1%
b11111010 (
b11111001 *
b11111110 +
b11111001 ,
#545
0%
#546
1%
b11111001 (
b11111000 *
b11111101 +
b11111000 ,
#547
0%
#548
1%
b11111000 (
b11110111 *
b11111100 +
b11110111 ,
#549
0%
#550
1%
b11110111 (
b11110110 *
b11111011 +
b11110110 ,
#551
0%
#552
1%
b11110110 (
b11110101 *
b11111010 +
b11110101 ,
#553
0%
#554
1%
1&
b11110101 (
b11110100 *
b11111001 +
b11110100 ,
#555
0%
#556
1%
0&
b00001111111100000000001100010011 '
b00000000 (
b11111111 *
b00000100 +
b11111111 ,
#557
0%
#558
1%
b00000000000000000000000000000000 '
b11111111 (
b11111110 *
b00000011 +
b11111110 ,
#559
0%
#560
1%
b11111110 (
b11111101 *
b00000010 +
b11111101 ,
#561
0%
#562
1%
b11111101 (
b11111100 *
b00000001 +
b11111100 ,
#563
0%
#564
1%
b11111100 (
b11111011 *
b00000000 +
b11111011 ,
#565
0%
#566
1%
b11111011 (
b11111010 *
b11111111 +
b11111010 ,
#567
0%
#568
1%
b11111010 (
b11111001 *
b11111110 +
b11111001 ,
#569
0%
#570
1%
b11111001 (
b11111000 *
b11111101 +
b11111000 ,
#571
0%
#572
1%
b11111000 (
b11110111 *
b11111100 +
b11110111 ,
#573
0%
#574
1%
b11110111 (
b11110110 *
b11111011 +
b11110110 ,
#575
0%
#576
1%
b11110110 (
b11110101 *
b11111010 +
b11110101 ,
#577
0%
#578
1%
1&
b11110101 (
b11110100 *
b11111001 +
b11110100 ,
#579
0%
#580
1%
0&
b00001111111100000000001100010011 '
b00000000 (
b11111111 *
b00000100 +
b11111111 ,
#581
0%
#582
1%
b00000000000000000000000000000000 '
b11111111 (
b11111110 *
b00000011 +
b11111110 ,
#583
0%
#584
1%
b11111110 (
b11111101 *
b00000010 +
b11111101 ,
#585
0%
#586
1%
b11111101 (
b11111100 *
b00000001 +
b11111100 ,
#587
0%
#588
1%
b11111100 (
b11111011 *
b00000000 +
b11111011 ,
#589
0%
#590
1%
b11111011 (
b11111010 *
b11111111 +
b11111010 ,
#591
0%
#592
1%
b11111010 (
b11111001 *
b11111110 +
b11111001 ,
#593
0%
